// 
// Decompiled by Procyon v0.5.36
// 

package com.google.android.gms.internal;

import java.io.IOException;
import org.apache.http.HttpEntity;
import java.util.Comparator;
import java.util.TreeMap;
import java.util.Map;
import org.apache.http.Header;

public final class zzad implements zzk
{
    private static boolean DEBUG;
    private static int zzam;
    private static int zzan;
    private zzan zzao;
    private zzae zzap;
    
    static {
        zzad.DEBUG = zzab.DEBUG;
        zzad.zzam = 3000;
        zzad.zzan = 4096;
    }
    
    public zzad(final zzan zzan) {
        this(zzan, new zzae(zzad.zzan));
    }
    
    private zzad(final zzan zzao, final zzae zzap) {
        this.zzao = zzao;
        this.zzap = zzap;
    }
    
    private static Map<String, String> zza(final Header[] array) {
        final TreeMap<String, String> treeMap = new TreeMap<String, String>(String.CASE_INSENSITIVE_ORDER);
        for (int i = 0; i < array.length; ++i) {
            treeMap.put(array[i].getName(), array[i].getValue());
        }
        return treeMap;
    }
    
    private static void zza(final String s, final zzp<?> zzp, final zzaa zzaa) throws zzaa {
        final zzx zzj = zzp.zzj();
        final int zzi = zzp.zzi();
        try {
            zzj.zza(zzaa);
            zzp.zzb(String.format("%s-retry [timeout=%s]", s, zzi));
        }
        catch (zzaa zzaa) {
            zzp.zzb(String.format("%s-timeout-giveup [timeout=%s]", s, zzi));
            throw zzaa;
        }
    }
    
    private final byte[] zza(final HttpEntity p0) throws IOException, zzy {
        // 
        // This method could not be decompiled.
        // 
        // Original Bytecode:
        // 
        //     3: dup            
        //     4: aload_0        
        //     5: getfield        com/google/android/gms/internal/zzad.zzap:Lcom/google/android/gms/internal/zzae;
        //     8: aload_1        
        //     9: invokeinterface org/apache/http/HttpEntity.getContentLength:()J
        //    14: l2i            
        //    15: invokespecial   com/google/android/gms/internal/zzaq.<init>:(Lcom/google/android/gms/internal/zzae;I)V
        //    18: astore          5
        //    20: aconst_null    
        //    21: astore          4
        //    23: aload           4
        //    25: astore_3       
        //    26: aload_1        
        //    27: invokeinterface org/apache/http/HttpEntity.getContent:()Ljava/io/InputStream;
        //    32: astore          6
        //    34: aload           6
        //    36: ifnonnull       74
        //    39: aload           4
        //    41: astore_3       
        //    42: new             Lcom/google/android/gms/internal/zzy;
        //    45: dup            
        //    46: invokespecial   com/google/android/gms/internal/zzy.<init>:()V
        //    49: athrow         
        //    50: astore          4
        //    52: aload_1        
        //    53: invokeinterface org/apache/http/HttpEntity.consumeContent:()V
        //    58: aload_0        
        //    59: getfield        com/google/android/gms/internal/zzad.zzap:Lcom/google/android/gms/internal/zzae;
        //    62: aload_3        
        //    63: invokevirtual   com/google/android/gms/internal/zzae.zza:([B)V
        //    66: aload           5
        //    68: invokevirtual   com/google/android/gms/internal/zzaq.close:()V
        //    71: aload           4
        //    73: athrow         
        //    74: aload           4
        //    76: astore_3       
        //    77: aload_0        
        //    78: getfield        com/google/android/gms/internal/zzad.zzap:Lcom/google/android/gms/internal/zzae;
        //    81: sipush          1024
        //    84: invokevirtual   com/google/android/gms/internal/zzae.zzb:(I)[B
        //    87: astore          4
        //    89: aload           4
        //    91: astore_3       
        //    92: aload           6
        //    94: aload           4
        //    96: invokevirtual   java/io/InputStream.read:([B)I
        //    99: istore_2       
        //   100: iload_2        
        //   101: iconst_m1      
        //   102: if_icmpeq       120
        //   105: aload           4
        //   107: astore_3       
        //   108: aload           5
        //   110: aload           4
        //   112: iconst_0       
        //   113: iload_2        
        //   114: invokevirtual   com/google/android/gms/internal/zzaq.write:([BII)V
        //   117: goto            89
        //   120: aload           4
        //   122: astore_3       
        //   123: aload           5
        //   125: invokevirtual   com/google/android/gms/internal/zzaq.toByteArray:()[B
        //   128: astore          6
        //   130: aload_1        
        //   131: invokeinterface org/apache/http/HttpEntity.consumeContent:()V
        //   136: aload_0        
        //   137: getfield        com/google/android/gms/internal/zzad.zzap:Lcom/google/android/gms/internal/zzae;
        //   140: aload           4
        //   142: invokevirtual   com/google/android/gms/internal/zzae.zza:([B)V
        //   145: aload           5
        //   147: invokevirtual   com/google/android/gms/internal/zzaq.close:()V
        //   150: aload           6
        //   152: areturn        
        //   153: astore_1       
        //   154: ldc             "Error occured when calling consumingContent"
        //   156: iconst_0       
        //   157: anewarray       Ljava/lang/Object;
        //   160: invokestatic    com/google/android/gms/internal/zzab.zza:(Ljava/lang/String;[Ljava/lang/Object;)V
        //   163: goto            136
        //   166: astore_1       
        //   167: ldc             "Error occured when calling consumingContent"
        //   169: iconst_0       
        //   170: anewarray       Ljava/lang/Object;
        //   173: invokestatic    com/google/android/gms/internal/zzab.zza:(Ljava/lang/String;[Ljava/lang/Object;)V
        //   176: goto            58
        //    Exceptions:
        //  throws java.io.IOException
        //  throws com.google.android.gms.internal.zzy
        //    Exceptions:
        //  Try           Handler
        //  Start  End    Start  End    Type                 
        //  -----  -----  -----  -----  ---------------------
        //  26     34     50     74     Any
        //  42     50     50     74     Any
        //  52     58     166    179    Ljava/io/IOException;
        //  77     89     50     74     Any
        //  92     100    50     74     Any
        //  108    117    50     74     Any
        //  123    130    50     74     Any
        //  130    136    153    166    Ljava/io/IOException;
        // 
        // The error that occurred was:
        // 
        // java.lang.IllegalStateException: Expression is linked from several locations: Label_0058:
        //     at com.strobel.decompiler.ast.Error.expressionLinkedFromMultipleLocations(Error.java:27)
        //     at com.strobel.decompiler.ast.AstOptimizer.mergeDisparateObjectInitializations(AstOptimizer.java:2596)
        //     at com.strobel.decompiler.ast.AstOptimizer.optimize(AstOptimizer.java:235)
        //     at com.strobel.decompiler.ast.AstOptimizer.optimize(AstOptimizer.java:42)
        //     at com.strobel.decompiler.languages.java.ast.AstMethodBodyBuilder.createMethodBody(AstMethodBodyBuilder.java:214)
        //     at com.strobel.decompiler.languages.java.ast.AstMethodBodyBuilder.createMethodBody(AstMethodBodyBuilder.java:99)
        //     at com.strobel.decompiler.languages.java.ast.AstBuilder.createMethodBody(AstBuilder.java:782)
        //     at com.strobel.decompiler.languages.java.ast.AstBuilder.createMethod(AstBuilder.java:675)
        //     at com.strobel.decompiler.languages.java.ast.AstBuilder.addTypeMembers(AstBuilder.java:552)
        //     at com.strobel.decompiler.languages.java.ast.AstBuilder.createTypeCore(AstBuilder.java:519)
        //     at com.strobel.decompiler.languages.java.ast.AstBuilder.createTypeNoCache(AstBuilder.java:161)
        //     at com.strobel.decompiler.languages.java.ast.AstBuilder.createType(AstBuilder.java:150)
        //     at com.strobel.decompiler.languages.java.ast.AstBuilder.addType(AstBuilder.java:125)
        //     at com.strobel.decompiler.languages.java.JavaLanguage.buildAst(JavaLanguage.java:71)
        //     at com.strobel.decompiler.languages.java.JavaLanguage.decompileType(JavaLanguage.java:59)
        //     at com.strobel.decompiler.DecompilerDriver.decompileType(DecompilerDriver.java:330)
        //     at com.strobel.decompiler.DecompilerDriver.decompileJar(DecompilerDriver.java:251)
        //     at com.strobel.decompiler.DecompilerDriver.main(DecompilerDriver.java:126)
        // 
        throw new IllegalStateException("An error occurred while decompiling this method.");
    }
    
    @Override
    public final zzn zza(final zzp<?> p0) throws zzaa {
        // 
        // This method could not be decompiled.
        // 
        // Original Bytecode:
        // 
        //     3: lstore_3       
        //     4: aconst_null    
        //     5: astore          11
        //     7: invokestatic    java/util/Collections.emptyMap:()Ljava/util/Map;
        //    10: astore          9
        //    12: new             Ljava/util/HashMap;
        //    15: dup            
        //    16: invokespecial   java/util/HashMap.<init>:()V
        //    19: astore          7
        //    21: aload_1        
        //    22: invokevirtual   com/google/android/gms/internal/zzp.zze:()Lcom/google/android/gms/internal/zzc;
        //    25: astore          8
        //    27: aload           8
        //    29: ifnull          90
        //    32: aload           8
        //    34: getfield        com/google/android/gms/internal/zzc.zza:Ljava/lang/String;
        //    37: ifnull          55
        //    40: aload           7
        //    42: ldc             "If-None-Match"
        //    44: aload           8
        //    46: getfield        com/google/android/gms/internal/zzc.zza:Ljava/lang/String;
        //    49: invokeinterface java/util/Map.put:(Ljava/lang/Object;Ljava/lang/Object;)Ljava/lang/Object;
        //    54: pop            
        //    55: aload           8
        //    57: getfield        com/google/android/gms/internal/zzc.zzc:J
        //    60: lconst_0       
        //    61: lcmp           
        //    62: ifle            90
        //    65: aload           7
        //    67: ldc             "If-Modified-Since"
        //    69: new             Ljava/util/Date;
        //    72: dup            
        //    73: aload           8
        //    75: getfield        com/google/android/gms/internal/zzc.zzc:J
        //    78: invokespecial   java/util/Date.<init>:(J)V
        //    81: invokestatic    org/apache/http/impl/cookie/DateUtils.formatDate:(Ljava/util/Date;)Ljava/lang/String;
        //    84: invokeinterface java/util/Map.put:(Ljava/lang/Object;Ljava/lang/Object;)Ljava/lang/Object;
        //    89: pop            
        //    90: aload_0        
        //    91: getfield        com/google/android/gms/internal/zzad.zzao:Lcom/google/android/gms/internal/zzan;
        //    94: aload_1        
        //    95: aload           7
        //    97: invokeinterface com/google/android/gms/internal/zzan.zza:(Lcom/google/android/gms/internal/zzp;Ljava/util/Map;)Lorg/apache/http/HttpResponse;
        //   102: astore          8
        //   104: aload           9
        //   106: astore          7
        //   108: aload           8
        //   110: invokeinterface org/apache/http/HttpResponse.getStatusLine:()Lorg/apache/http/StatusLine;
        //   115: astore          10
        //   117: aload           9
        //   119: astore          7
        //   121: aload           10
        //   123: invokeinterface org/apache/http/StatusLine.getStatusCode:()I
        //   128: istore_2       
        //   129: aload           9
        //   131: astore          7
        //   133: aload           8
        //   135: invokeinterface org/apache/http/HttpResponse.getAllHeaders:()[Lorg/apache/http/Header;
        //   140: invokestatic    com/google/android/gms/internal/zzad.zza:([Lorg/apache/http/Header;)Ljava/util/Map;
        //   143: astore          11
        //   145: iload_2        
        //   146: sipush          304
        //   149: if_icmpne       238
        //   152: aload           11
        //   154: astore          7
        //   156: aload_1        
        //   157: invokevirtual   com/google/android/gms/internal/zzp.zze:()Lcom/google/android/gms/internal/zzc;
        //   160: astore          9
        //   162: aload           9
        //   164: ifnonnull       191
        //   167: aload           11
        //   169: astore          7
        //   171: new             Lcom/google/android/gms/internal/zzn;
        //   174: dup            
        //   175: sipush          304
        //   178: aconst_null    
        //   179: aload           11
        //   181: iconst_1       
        //   182: invokestatic    android/os/SystemClock.elapsedRealtime:()J
        //   185: lload_3        
        //   186: lsub           
        //   187: invokespecial   com/google/android/gms/internal/zzn.<init>:(I[BLjava/util/Map;ZJ)V
        //   190: areturn        
        //   191: aload           11
        //   193: astore          7
        //   195: aload           9
        //   197: getfield        com/google/android/gms/internal/zzc.zzf:Ljava/util/Map;
        //   200: aload           11
        //   202: invokeinterface java/util/Map.putAll:(Ljava/util/Map;)V
        //   207: aload           11
        //   209: astore          7
        //   211: new             Lcom/google/android/gms/internal/zzn;
        //   214: dup            
        //   215: sipush          304
        //   218: aload           9
        //   220: getfield        com/google/android/gms/internal/zzc.data:[B
        //   223: aload           9
        //   225: getfield        com/google/android/gms/internal/zzc.zzf:Ljava/util/Map;
        //   228: iconst_1       
        //   229: invokestatic    android/os/SystemClock.elapsedRealtime:()J
        //   232: lload_3        
        //   233: lsub           
        //   234: invokespecial   com/google/android/gms/internal/zzn.<init>:(I[BLjava/util/Map;ZJ)V
        //   237: areturn        
        //   238: aload           11
        //   240: astore          7
        //   242: aload           8
        //   244: invokeinterface org/apache/http/HttpResponse.getEntity:()Lorg/apache/http/HttpEntity;
        //   249: ifnull          394
        //   252: aload           11
        //   254: astore          7
        //   256: aload_0        
        //   257: aload           8
        //   259: invokeinterface org/apache/http/HttpResponse.getEntity:()Lorg/apache/http/HttpEntity;
        //   264: invokespecial   com/google/android/gms/internal/zzad.zza:(Lorg/apache/http/HttpEntity;)[B
        //   267: astore          9
        //   269: aload           9
        //   271: astore          7
        //   273: invokestatic    android/os/SystemClock.elapsedRealtime:()J
        //   276: lload_3        
        //   277: lsub           
        //   278: lstore          5
        //   280: getstatic       com/google/android/gms/internal/zzad.DEBUG:Z
        //   283: ifne            296
        //   286: lload           5
        //   288: getstatic       com/google/android/gms/internal/zzad.zzam:I
        //   291: i2l            
        //   292: lcmp           
        //   293: ifle            745
        //   296: aload           7
        //   298: ifnull          410
        //   301: aload           7
        //   303: arraylength    
        //   304: invokestatic    java/lang/Integer.valueOf:(I)Ljava/lang/Integer;
        //   307: astore          9
        //   309: ldc_w           "HTTP response for request=<%s> [lifetime=%d], [size=%s], [rc=%d], [retryCount=%s]"
        //   312: iconst_5       
        //   313: anewarray       Ljava/lang/Object;
        //   316: dup            
        //   317: iconst_0       
        //   318: aload_1        
        //   319: aastore        
        //   320: dup            
        //   321: iconst_1       
        //   322: lload           5
        //   324: invokestatic    java/lang/Long.valueOf:(J)Ljava/lang/Long;
        //   327: aastore        
        //   328: dup            
        //   329: iconst_2       
        //   330: aload           9
        //   332: aastore        
        //   333: dup            
        //   334: iconst_3       
        //   335: aload           10
        //   337: invokeinterface org/apache/http/StatusLine.getStatusCode:()I
        //   342: invokestatic    java/lang/Integer.valueOf:(I)Ljava/lang/Integer;
        //   345: aastore        
        //   346: dup            
        //   347: iconst_4       
        //   348: aload_1        
        //   349: invokevirtual   com/google/android/gms/internal/zzp.zzj:()Lcom/google/android/gms/internal/zzx;
        //   352: invokeinterface com/google/android/gms/internal/zzx.zzb:()I
        //   357: invokestatic    java/lang/Integer.valueOf:(I)Ljava/lang/Integer;
        //   360: aastore        
        //   361: invokestatic    com/google/android/gms/internal/zzab.zzb:(Ljava/lang/String;[Ljava/lang/Object;)V
        //   364: goto            745
        //   367: new             Ljava/io/IOException;
        //   370: dup            
        //   371: invokespecial   java/io/IOException.<init>:()V
        //   374: athrow         
        //   375: astore          7
        //   377: ldc_w           "socket"
        //   380: aload_1        
        //   381: new             Lcom/google/android/gms/internal/zzz;
        //   384: dup            
        //   385: invokespecial   com/google/android/gms/internal/zzz.<init>:()V
        //   388: invokestatic    com/google/android/gms/internal/zzad.zza:(Ljava/lang/String;Lcom/google/android/gms/internal/zzp;Lcom/google/android/gms/internal/zzaa;)V
        //   391: goto            4
        //   394: aload           11
        //   396: astore          7
        //   398: iconst_0       
        //   399: newarray        B
        //   401: astore          9
        //   403: aload           9
        //   405: astore          7
        //   407: goto            273
        //   410: ldc_w           "null"
        //   413: astore          9
        //   415: goto            309
        //   418: new             Lcom/google/android/gms/internal/zzn;
        //   421: dup            
        //   422: iload_2        
        //   423: aload           7
        //   425: aload           11
        //   427: iconst_0       
        //   428: invokestatic    android/os/SystemClock.elapsedRealtime:()J
        //   431: lload_3        
        //   432: lsub           
        //   433: invokespecial   com/google/android/gms/internal/zzn.<init>:(I[BLjava/util/Map;ZJ)V
        //   436: astore          9
        //   438: aload           9
        //   440: areturn        
        //   441: astore          7
        //   443: ldc_w           "connection"
        //   446: aload_1        
        //   447: new             Lcom/google/android/gms/internal/zzz;
        //   450: dup            
        //   451: invokespecial   com/google/android/gms/internal/zzz.<init>:()V
        //   454: invokestatic    com/google/android/gms/internal/zzad.zza:(Ljava/lang/String;Lcom/google/android/gms/internal/zzp;Lcom/google/android/gms/internal/zzaa;)V
        //   457: goto            4
        //   460: astore          7
        //   462: aload_1        
        //   463: invokevirtual   com/google/android/gms/internal/zzp.getUrl:()Ljava/lang/String;
        //   466: invokestatic    java/lang/String.valueOf:(Ljava/lang/Object;)Ljava/lang/String;
        //   469: astore_1       
        //   470: aload_1        
        //   471: invokevirtual   java/lang/String.length:()I
        //   474: ifeq            496
        //   477: ldc_w           "Bad URL "
        //   480: aload_1        
        //   481: invokevirtual   java/lang/String.concat:(Ljava/lang/String;)Ljava/lang/String;
        //   484: astore_1       
        //   485: new             Ljava/lang/RuntimeException;
        //   488: dup            
        //   489: aload_1        
        //   490: aload           7
        //   492: invokespecial   java/lang/RuntimeException.<init>:(Ljava/lang/String;Ljava/lang/Throwable;)V
        //   495: athrow         
        //   496: new             Ljava/lang/String;
        //   499: dup            
        //   500: ldc_w           "Bad URL "
        //   503: invokespecial   java/lang/String.<init>:(Ljava/lang/String;)V
        //   506: astore_1       
        //   507: goto            485
        //   510: astore          8
        //   512: aconst_null    
        //   513: astore          10
        //   515: aload           9
        //   517: astore          7
        //   519: aload           11
        //   521: astore          9
        //   523: aload           9
        //   525: ifnull          623
        //   528: aload           9
        //   530: invokeinterface org/apache/http/HttpResponse.getStatusLine:()Lorg/apache/http/StatusLine;
        //   535: invokeinterface org/apache/http/StatusLine.getStatusCode:()I
        //   540: istore_2       
        //   541: ldc_w           "Unexpected response code %d for %s"
        //   544: iconst_2       
        //   545: anewarray       Ljava/lang/Object;
        //   548: dup            
        //   549: iconst_0       
        //   550: iload_2        
        //   551: invokestatic    java/lang/Integer.valueOf:(I)Ljava/lang/Integer;
        //   554: aastore        
        //   555: dup            
        //   556: iconst_1       
        //   557: aload_1        
        //   558: invokevirtual   com/google/android/gms/internal/zzp.getUrl:()Ljava/lang/String;
        //   561: aastore        
        //   562: invokestatic    com/google/android/gms/internal/zzab.zzc:(Ljava/lang/String;[Ljava/lang/Object;)V
        //   565: aload           10
        //   567: ifnull          691
        //   570: new             Lcom/google/android/gms/internal/zzn;
        //   573: dup            
        //   574: iload_2        
        //   575: aload           10
        //   577: aload           7
        //   579: iconst_0       
        //   580: invokestatic    android/os/SystemClock.elapsedRealtime:()J
        //   583: lload_3        
        //   584: lsub           
        //   585: invokespecial   com/google/android/gms/internal/zzn.<init>:(I[BLjava/util/Map;ZJ)V
        //   588: astore          7
        //   590: iload_2        
        //   591: sipush          401
        //   594: if_icmpeq       604
        //   597: iload_2        
        //   598: sipush          403
        //   601: if_icmpne       633
        //   604: ldc_w           "auth"
        //   607: aload_1        
        //   608: new             Lcom/google/android/gms/internal/zza;
        //   611: dup            
        //   612: aload           7
        //   614: invokespecial   com/google/android/gms/internal/zza.<init>:(Lcom/google/android/gms/internal/zzn;)V
        //   617: invokestatic    com/google/android/gms/internal/zzad.zza:(Ljava/lang/String;Lcom/google/android/gms/internal/zzp;Lcom/google/android/gms/internal/zzaa;)V
        //   620: goto            4
        //   623: new             Lcom/google/android/gms/internal/zzo;
        //   626: dup            
        //   627: aload           8
        //   629: invokespecial   com/google/android/gms/internal/zzo.<init>:(Ljava/lang/Throwable;)V
        //   632: athrow         
        //   633: iload_2        
        //   634: sipush          400
        //   637: if_icmplt       657
        //   640: iload_2        
        //   641: sipush          499
        //   644: if_icmpgt       657
        //   647: new             Lcom/google/android/gms/internal/zzf;
        //   650: dup            
        //   651: aload           7
        //   653: invokespecial   com/google/android/gms/internal/zzf.<init>:(Lcom/google/android/gms/internal/zzn;)V
        //   656: athrow         
        //   657: iload_2        
        //   658: sipush          500
        //   661: if_icmplt       681
        //   664: iload_2        
        //   665: sipush          599
        //   668: if_icmpgt       681
        //   671: new             Lcom/google/android/gms/internal/zzy;
        //   674: dup            
        //   675: aload           7
        //   677: invokespecial   com/google/android/gms/internal/zzy.<init>:(Lcom/google/android/gms/internal/zzn;)V
        //   680: athrow         
        //   681: new             Lcom/google/android/gms/internal/zzy;
        //   684: dup            
        //   685: aload           7
        //   687: invokespecial   com/google/android/gms/internal/zzy.<init>:(Lcom/google/android/gms/internal/zzn;)V
        //   690: athrow         
        //   691: ldc_w           "network"
        //   694: aload_1        
        //   695: new             Lcom/google/android/gms/internal/zzm;
        //   698: dup            
        //   699: invokespecial   com/google/android/gms/internal/zzm.<init>:()V
        //   702: invokestatic    com/google/android/gms/internal/zzad.zza:(Ljava/lang/String;Lcom/google/android/gms/internal/zzp;Lcom/google/android/gms/internal/zzaa;)V
        //   705: goto            4
        //   708: astore          11
        //   710: aconst_null    
        //   711: astore          10
        //   713: aload           8
        //   715: astore          9
        //   717: aload           11
        //   719: astore          8
        //   721: goto            523
        //   724: astore          10
        //   726: aload           8
        //   728: astore          9
        //   730: aload           10
        //   732: astore          8
        //   734: aload           7
        //   736: astore          10
        //   738: aload           11
        //   740: astore          7
        //   742: goto            523
        //   745: iload_2        
        //   746: sipush          200
        //   749: if_icmplt       367
        //   752: iload_2        
        //   753: sipush          299
        //   756: if_icmple       418
        //   759: goto            367
        //    Exceptions:
        //  throws com.google.android.gms.internal.zzaa
        //    Signature:
        //  (Lcom/google/android/gms/internal/zzp<*>;)Lcom/google/android/gms/internal/zzn;
        //    Exceptions:
        //  Try           Handler
        //  Start  End    Start  End    Type                                          
        //  -----  -----  -----  -----  ----------------------------------------------
        //  12     27     375    394    Ljava/net/SocketTimeoutException;
        //  12     27     441    460    Lorg/apache/http/conn/ConnectTimeoutException;
        //  12     27     460    510    Ljava/net/MalformedURLException;
        //  12     27     510    523    Ljava/io/IOException;
        //  32     55     375    394    Ljava/net/SocketTimeoutException;
        //  32     55     441    460    Lorg/apache/http/conn/ConnectTimeoutException;
        //  32     55     460    510    Ljava/net/MalformedURLException;
        //  32     55     510    523    Ljava/io/IOException;
        //  55     90     375    394    Ljava/net/SocketTimeoutException;
        //  55     90     441    460    Lorg/apache/http/conn/ConnectTimeoutException;
        //  55     90     460    510    Ljava/net/MalformedURLException;
        //  55     90     510    523    Ljava/io/IOException;
        //  90     104    375    394    Ljava/net/SocketTimeoutException;
        //  90     104    441    460    Lorg/apache/http/conn/ConnectTimeoutException;
        //  90     104    460    510    Ljava/net/MalformedURLException;
        //  90     104    510    523    Ljava/io/IOException;
        //  108    117    375    394    Ljava/net/SocketTimeoutException;
        //  108    117    441    460    Lorg/apache/http/conn/ConnectTimeoutException;
        //  108    117    460    510    Ljava/net/MalformedURLException;
        //  108    117    708    724    Ljava/io/IOException;
        //  121    129    375    394    Ljava/net/SocketTimeoutException;
        //  121    129    441    460    Lorg/apache/http/conn/ConnectTimeoutException;
        //  121    129    460    510    Ljava/net/MalformedURLException;
        //  121    129    708    724    Ljava/io/IOException;
        //  133    145    375    394    Ljava/net/SocketTimeoutException;
        //  133    145    441    460    Lorg/apache/http/conn/ConnectTimeoutException;
        //  133    145    460    510    Ljava/net/MalformedURLException;
        //  133    145    708    724    Ljava/io/IOException;
        //  156    162    375    394    Ljava/net/SocketTimeoutException;
        //  156    162    441    460    Lorg/apache/http/conn/ConnectTimeoutException;
        //  156    162    460    510    Ljava/net/MalformedURLException;
        //  156    162    708    724    Ljava/io/IOException;
        //  171    191    375    394    Ljava/net/SocketTimeoutException;
        //  171    191    441    460    Lorg/apache/http/conn/ConnectTimeoutException;
        //  171    191    460    510    Ljava/net/MalformedURLException;
        //  171    191    708    724    Ljava/io/IOException;
        //  195    207    375    394    Ljava/net/SocketTimeoutException;
        //  195    207    441    460    Lorg/apache/http/conn/ConnectTimeoutException;
        //  195    207    460    510    Ljava/net/MalformedURLException;
        //  195    207    708    724    Ljava/io/IOException;
        //  211    238    375    394    Ljava/net/SocketTimeoutException;
        //  211    238    441    460    Lorg/apache/http/conn/ConnectTimeoutException;
        //  211    238    460    510    Ljava/net/MalformedURLException;
        //  211    238    708    724    Ljava/io/IOException;
        //  242    252    375    394    Ljava/net/SocketTimeoutException;
        //  242    252    441    460    Lorg/apache/http/conn/ConnectTimeoutException;
        //  242    252    460    510    Ljava/net/MalformedURLException;
        //  242    252    708    724    Ljava/io/IOException;
        //  256    269    375    394    Ljava/net/SocketTimeoutException;
        //  256    269    441    460    Lorg/apache/http/conn/ConnectTimeoutException;
        //  256    269    460    510    Ljava/net/MalformedURLException;
        //  256    269    708    724    Ljava/io/IOException;
        //  273    296    375    394    Ljava/net/SocketTimeoutException;
        //  273    296    441    460    Lorg/apache/http/conn/ConnectTimeoutException;
        //  273    296    460    510    Ljava/net/MalformedURLException;
        //  273    296    724    745    Ljava/io/IOException;
        //  301    309    375    394    Ljava/net/SocketTimeoutException;
        //  301    309    441    460    Lorg/apache/http/conn/ConnectTimeoutException;
        //  301    309    460    510    Ljava/net/MalformedURLException;
        //  301    309    724    745    Ljava/io/IOException;
        //  309    364    375    394    Ljava/net/SocketTimeoutException;
        //  309    364    441    460    Lorg/apache/http/conn/ConnectTimeoutException;
        //  309    364    460    510    Ljava/net/MalformedURLException;
        //  309    364    724    745    Ljava/io/IOException;
        //  367    375    375    394    Ljava/net/SocketTimeoutException;
        //  367    375    441    460    Lorg/apache/http/conn/ConnectTimeoutException;
        //  367    375    460    510    Ljava/net/MalformedURLException;
        //  367    375    724    745    Ljava/io/IOException;
        //  398    403    375    394    Ljava/net/SocketTimeoutException;
        //  398    403    441    460    Lorg/apache/http/conn/ConnectTimeoutException;
        //  398    403    460    510    Ljava/net/MalformedURLException;
        //  398    403    708    724    Ljava/io/IOException;
        //  418    438    375    394    Ljava/net/SocketTimeoutException;
        //  418    438    441    460    Lorg/apache/http/conn/ConnectTimeoutException;
        //  418    438    460    510    Ljava/net/MalformedURLException;
        //  418    438    724    745    Ljava/io/IOException;
        // 
        // The error that occurred was:
        // 
        // java.util.ConcurrentModificationException
        //     at java.base/java.util.ArrayList$Itr.checkForComodification(ArrayList.java:1042)
        //     at java.base/java.util.ArrayList$Itr.next(ArrayList.java:996)
        //     at com.strobel.decompiler.ast.AstBuilder.convertLocalVariables(AstBuilder.java:2863)
        //     at com.strobel.decompiler.ast.AstBuilder.performStackAnalysis(AstBuilder.java:2445)
        //     at com.strobel.decompiler.ast.AstBuilder.build(AstBuilder.java:108)
        //     at com.strobel.decompiler.languages.java.ast.AstMethodBodyBuilder.createMethodBody(AstMethodBodyBuilder.java:211)
        //     at com.strobel.decompiler.languages.java.ast.AstMethodBodyBuilder.createMethodBody(AstMethodBodyBuilder.java:99)
        //     at com.strobel.decompiler.languages.java.ast.AstBuilder.createMethodBody(AstBuilder.java:782)
        //     at com.strobel.decompiler.languages.java.ast.AstBuilder.createMethod(AstBuilder.java:675)
        //     at com.strobel.decompiler.languages.java.ast.AstBuilder.addTypeMembers(AstBuilder.java:552)
        //     at com.strobel.decompiler.languages.java.ast.AstBuilder.createTypeCore(AstBuilder.java:519)
        //     at com.strobel.decompiler.languages.java.ast.AstBuilder.createTypeNoCache(AstBuilder.java:161)
        //     at com.strobel.decompiler.languages.java.ast.AstBuilder.createType(AstBuilder.java:150)
        //     at com.strobel.decompiler.languages.java.ast.AstBuilder.addType(AstBuilder.java:125)
        //     at com.strobel.decompiler.languages.java.JavaLanguage.buildAst(JavaLanguage.java:71)
        //     at com.strobel.decompiler.languages.java.JavaLanguage.decompileType(JavaLanguage.java:59)
        //     at com.strobel.decompiler.DecompilerDriver.decompileType(DecompilerDriver.java:330)
        //     at com.strobel.decompiler.DecompilerDriver.decompileJar(DecompilerDriver.java:251)
        //     at com.strobel.decompiler.DecompilerDriver.main(DecompilerDriver.java:126)
        // 
        throw new IllegalStateException("An error occurred while decompiling this method.");
    }
}
