// 
// Decompiled by Procyon v0.5.36
// 

package com.google.android.gms.internal;

import android.support.annotation.WorkerThread;
import java.util.ArrayList;
import java.util.Arrays;
import com.google.android.gms.common.internal.zzbo;
import java.util.regex.PatternSyntaxException;
import java.util.regex.Pattern;
import java.util.Locale;
import java.util.List;
import android.support.v4.util.ArrayMap;
import android.text.TextUtils;
import java.util.HashSet;
import java.math.BigDecimal;

final class zzcej extends zzchj
{
    zzcej(final zzcgl zzcgl) {
        super(zzcgl);
    }
    
    private final Boolean zza(final double n, final zzcjp zzcjp) {
        try {
            return zza(new BigDecimal(n), zzcjp, Math.ulp(n));
        }
        catch (NumberFormatException ex) {
            return null;
        }
    }
    
    private final Boolean zza(final long val, final zzcjp zzcjp) {
        try {
            return zza(new BigDecimal(val), zzcjp, 0.0);
        }
        catch (NumberFormatException ex) {
            return null;
        }
    }
    
    private final Boolean zza(final zzcjn zzcjn, final zzcjw zzcjw, final long n) {
        if (zzcjn.zzbuQ != null) {
            final Boolean zza = this.zza(n, zzcjn.zzbuQ);
            if (zza == null) {
                return null;
            }
            if (!zza) {
                return false;
            }
        }
        final HashSet<String> set = new HashSet<String>();
        final zzcjo[] zzbuO = zzcjn.zzbuO;
        for (int length = zzbuO.length, i = 0; i < length; ++i) {
            final zzcjo zzcjo = zzbuO[i];
            if (TextUtils.isEmpty((CharSequence)zzcjo.zzbuV)) {
                this.zzwF().zzyz().zzj("null or empty param name in filter. event", this.zzwA().zzdW(zzcjw.name));
                return null;
            }
            set.add(zzcjo.zzbuV);
        }
        final ArrayMap<Object, String> arrayMap = new ArrayMap<Object, String>();
        final zzcjx[] zzbvw = zzcjw.zzbvw;
        for (int length2 = zzbvw.length, j = 0; j < length2; ++j) {
            final zzcjx zzcjx = zzbvw[j];
            if (set.contains(zzcjx.name)) {
                if (zzcjx.zzbvA != null) {
                    arrayMap.put(zzcjx.name, (String)zzcjx.zzbvA);
                }
                else if (zzcjx.zzbuB != null) {
                    arrayMap.put(zzcjx.name, (String)zzcjx.zzbuB);
                }
                else {
                    if (zzcjx.zzaIF == null) {
                        this.zzwF().zzyz().zze("Unknown value for param. event, param", this.zzwA().zzdW(zzcjw.name), this.zzwA().zzdX(zzcjx.name));
                        return null;
                    }
                    arrayMap.put(zzcjx.name, zzcjx.zzaIF);
                }
            }
        }
        final zzcjo[] zzbuO2 = zzcjn.zzbuO;
        for (int length3 = zzbuO2.length, k = 0; k < length3; ++k) {
            final zzcjo zzcjo2 = zzbuO2[k];
            final boolean equals = Boolean.TRUE.equals(zzcjo2.zzbuU);
            final String zzbuV = zzcjo2.zzbuV;
            if (TextUtils.isEmpty((CharSequence)zzbuV)) {
                this.zzwF().zzyz().zzj("Event has empty param name. event", this.zzwA().zzdW(zzcjw.name));
                return null;
            }
            final Object value = arrayMap.get(zzbuV);
            if (value instanceof Long) {
                if (zzcjo2.zzbuT == null) {
                    this.zzwF().zzyz().zze("No number filter for long param. event, param", this.zzwA().zzdW(zzcjw.name), this.zzwA().zzdX(zzbuV));
                    return null;
                }
                final Boolean zza2 = this.zza((long)value, zzcjo2.zzbuT);
                if (zza2 == null) {
                    return null;
                }
                boolean b;
                if (!zza2) {
                    b = true;
                }
                else {
                    b = false;
                }
                if (b ^ equals) {
                    return false;
                }
            }
            else if (value instanceof Double) {
                if (zzcjo2.zzbuT == null) {
                    this.zzwF().zzyz().zze("No number filter for double param. event, param", this.zzwA().zzdW(zzcjw.name), this.zzwA().zzdX(zzbuV));
                    return null;
                }
                final Boolean zza3 = this.zza((double)value, zzcjo2.zzbuT);
                if (zza3 == null) {
                    return null;
                }
                boolean b2;
                if (!zza3) {
                    b2 = true;
                }
                else {
                    b2 = false;
                }
                if (b2 ^ equals) {
                    return false;
                }
            }
            else if (value instanceof String) {
                Boolean b3;
                if (zzcjo2.zzbuS != null) {
                    b3 = this.zza((String)value, zzcjo2.zzbuS);
                }
                else {
                    if (zzcjo2.zzbuT == null) {
                        this.zzwF().zzyz().zze("No filter for String param. event, param", this.zzwA().zzdW(zzcjw.name), this.zzwA().zzdX(zzbuV));
                        return null;
                    }
                    if (!zzcjl.zzez((String)value)) {
                        this.zzwF().zzyz().zze("Invalid param value for number filter. event, param", this.zzwA().zzdW(zzcjw.name), this.zzwA().zzdX(zzbuV));
                        return null;
                    }
                    b3 = this.zza((String)value, zzcjo2.zzbuT);
                }
                if (b3 == null) {
                    return null;
                }
                boolean b4;
                if (!b3) {
                    b4 = true;
                }
                else {
                    b4 = false;
                }
                if (b4 ^ equals) {
                    return false;
                }
            }
            else {
                if (value == null) {
                    this.zzwF().zzyD().zze("Missing param for filter. event, param", this.zzwA().zzdW(zzcjw.name), this.zzwA().zzdX(zzbuV));
                    return false;
                }
                this.zzwF().zzyz().zze("Unknown param type. event, param", this.zzwA().zzdW(zzcjw.name), this.zzwA().zzdX(zzbuV));
                return null;
            }
        }
        return true;
    }
    
    private static Boolean zza(final Boolean b, final boolean b2) {
        if (b == null) {
            return null;
        }
        return b ^ b2;
    }
    
    private final Boolean zza(final String s, int n, final boolean b, final String s2, final List<String> list, final String s3) {
        if (s == null) {
            return null;
        }
        if (n == 6) {
            if (list == null || list.size() == 0) {
                return null;
            }
        }
        else if (s2 == null) {
            return null;
        }
        String upperCase = s;
        if (!b) {
            if (n == 1) {
                upperCase = s;
            }
            else {
                upperCase = s.toUpperCase(Locale.ENGLISH);
            }
        }
        switch (n) {
            default: {
                return null;
            }
            case 1: {
                Label_0132: {
                    if (!b) {
                        break Label_0132;
                    }
                    n = 0;
                    try {
                        return Pattern.compile(s3, n).matcher(upperCase).matches();
                        n = 66;
                        return Pattern.compile(s3, n).matcher(upperCase).matches();
                    }
                    catch (PatternSyntaxException ex) {
                        this.zzwF().zzyz().zzj("Invalid regular expression in REGEXP audience filter. expression", s3);
                        return null;
                    }
                }
            }
            case 2: {
                return upperCase.startsWith(s2);
            }
            case 3: {
                return upperCase.endsWith(s2);
            }
            case 4: {
                return upperCase.contains(s2);
            }
            case 5: {
                return upperCase.equals(s2);
            }
            case 6: {
                return list.contains(upperCase);
            }
        }
    }
    
    private final Boolean zza(final String val, final zzcjp zzcjp) {
        if (!zzcjl.zzez(val)) {
            return null;
        }
        try {
            return zza(new BigDecimal(val), zzcjp, 0.0);
        }
        catch (NumberFormatException ex) {
            return null;
        }
    }
    
    private final Boolean zza(final String s, final zzcjr zzcjr) {
        int n = 0;
        String s2 = null;
        zzbo.zzu(zzcjr);
        if (s != null && zzcjr.zzbve != null && zzcjr.zzbve != 0) {
            if (zzcjr.zzbve == 6) {
                if (zzcjr.zzbvh == null || zzcjr.zzbvh.length == 0) {
                    return null;
                }
            }
            else if (zzcjr.zzbvf == null) {
                return null;
            }
            final int intValue = zzcjr.zzbve;
            final boolean b = zzcjr.zzbvg != null && zzcjr.zzbvg;
            String s3;
            if (b || intValue == 1 || intValue == 6) {
                s3 = zzcjr.zzbvf;
            }
            else {
                s3 = zzcjr.zzbvf.toUpperCase(Locale.ENGLISH);
            }
            List<String> list;
            if (zzcjr.zzbvh == null) {
                list = null;
            }
            else {
                final String[] zzbvh = zzcjr.zzbvh;
                if (b) {
                    list = Arrays.asList(zzbvh);
                }
                else {
                    final ArrayList<String> list2 = new ArrayList<String>();
                    final int length = zzbvh.length;
                    while (true) {
                        list = list2;
                        if (n >= length) {
                            break;
                        }
                        list2.add(zzbvh[n].toUpperCase(Locale.ENGLISH));
                        ++n;
                    }
                }
            }
            if (intValue == 1) {
                s2 = s3;
            }
            return this.zza(s, intValue, b, s3, list, s2);
        }
        return null;
    }
    
    private static Boolean zza(final BigDecimal bigDecimal, final zzcjp zzcjp, final double n) {
        final boolean b = true;
        final boolean b2 = true;
        final boolean b3 = true;
        final boolean b4 = true;
        boolean b5 = true;
        zzbo.zzu(zzcjp);
        if (zzcjp.zzbuW == null || zzcjp.zzbuW == 0) {
            return null;
        }
        if (zzcjp.zzbuW == 4) {
            if (zzcjp.zzbuZ == null || zzcjp.zzbva == null) {
                return null;
            }
        }
        else if (zzcjp.zzbuY == null) {
            return null;
        }
        final int intValue = zzcjp.zzbuW;
        BigDecimal val = null;
        BigDecimal val2 = null;
        BigDecimal val3 = null;
        Label_0202: {
        Label_0197:
            while (true) {
                Label_0161: {
                    if (zzcjp.zzbuW != 4) {
                        break Label_0161;
                    }
                    if (!zzcjl.zzez(zzcjp.zzbuZ) || !zzcjl.zzez(zzcjp.zzbva)) {
                        return null;
                    }
                    try {
                        val = new BigDecimal(zzcjp.zzbuZ);
                        val2 = new BigDecimal(zzcjp.zzbva);
                        val3 = null;
                        if (intValue != 4) {
                            break Label_0197;
                        }
                        if (val == null) {
                            return null;
                        }
                        break Label_0202;
                    }
                    catch (NumberFormatException ex) {
                        return null;
                    }
                }
                if (!zzcjl.zzez(zzcjp.zzbuY)) {
                    return null;
                }
                try {
                    val3 = new BigDecimal(zzcjp.zzbuY);
                    val = null;
                    val2 = null;
                    continue;
                }
                catch (NumberFormatException ex2) {
                    return null;
                }
                break;
            }
            if (val3 == null) {
                return null;
            }
        }
        switch (intValue) {
            default: {
                return null;
            }
            case 1: {
                if (bigDecimal.compareTo(val3) != -1) {
                    b5 = false;
                }
                return b5;
            }
            case 2: {
                return bigDecimal.compareTo(val3) == 1 && b;
            }
            case 3: {
                if (n != 0.0) {
                    return bigDecimal.compareTo(val3.subtract(new BigDecimal(n).multiply(new BigDecimal(2)))) == 1 && bigDecimal.compareTo(val3.add(new BigDecimal(n).multiply(new BigDecimal(2)))) == -1 && b2;
                }
                return bigDecimal.compareTo(val3) == 0 && b3;
            }
            case 4: {
                return bigDecimal.compareTo(val) != -1 && bigDecimal.compareTo(val2) != 1 && b4;
            }
        }
    }
    
    @WorkerThread
    final zzcjv[] zza(final String p0, final zzcjw[] p1, final zzckb[] p2) {
        // 
        // This method could not be decompiled.
        // 
        // Original Bytecode:
        // 
        //     1: invokestatic    com/google/android/gms/common/internal/zzbo.zzcF:(Ljava/lang/String;)Ljava/lang/String;
        //     4: pop            
        //     5: new             Ljava/util/HashSet;
        //     8: dup            
        //     9: invokespecial   java/util/HashSet.<init>:()V
        //    12: astore          15
        //    14: new             Landroid/support/v4/util/ArrayMap;
        //    17: dup            
        //    18: invokespecial   android/support/v4/util/ArrayMap.<init>:()V
        //    21: astore          16
        //    23: new             Landroid/support/v4/util/ArrayMap;
        //    26: dup            
        //    27: invokespecial   android/support/v4/util/ArrayMap.<init>:()V
        //    30: astore          17
        //    32: new             Landroid/support/v4/util/ArrayMap;
        //    35: dup            
        //    36: invokespecial   android/support/v4/util/ArrayMap.<init>:()V
        //    39: astore          18
        //    41: aload_0        
        //    42: invokevirtual   com/google/android/gms/internal/zzcej.zzwz:()Lcom/google/android/gms/internal/zzcen;
        //    45: aload_1        
        //    46: invokevirtual   com/google/android/gms/internal/zzcen.zzdT:(Ljava/lang/String;)Ljava/util/Map;
        //    49: astore          13
        //    51: aload           13
        //    53: ifnull          373
        //    56: aload           13
        //    58: invokeinterface java/util/Map.keySet:()Ljava/util/Set;
        //    63: invokeinterface java/util/Set.iterator:()Ljava/util/Iterator;
        //    68: astore          14
        //    70: aload           14
        //    72: invokeinterface java/util/Iterator.hasNext:()Z
        //    77: ifeq            373
        //    80: aload           14
        //    82: invokeinterface java/util/Iterator.next:()Ljava/lang/Object;
        //    87: checkcast       Ljava/lang/Integer;
        //    90: invokevirtual   java/lang/Integer.intValue:()I
        //    93: istore          5
        //    95: aload           13
        //    97: iload           5
        //    99: invokestatic    java/lang/Integer.valueOf:(I)Ljava/lang/Integer;
        //   102: invokeinterface java/util/Map.get:(Ljava/lang/Object;)Ljava/lang/Object;
        //   107: checkcast       Lcom/google/android/gms/internal/zzcka;
        //   110: astore          19
        //   112: aload           17
        //   114: iload           5
        //   116: invokestatic    java/lang/Integer.valueOf:(I)Ljava/lang/Integer;
        //   119: invokeinterface java/util/Map.get:(Ljava/lang/Object;)Ljava/lang/Object;
        //   124: checkcast       Ljava/util/BitSet;
        //   127: astore          12
        //   129: aload           18
        //   131: iload           5
        //   133: invokestatic    java/lang/Integer.valueOf:(I)Ljava/lang/Integer;
        //   136: invokeinterface java/util/Map.get:(Ljava/lang/Object;)Ljava/lang/Object;
        //   141: checkcast       Ljava/util/BitSet;
        //   144: astore          11
        //   146: aload           12
        //   148: astore          10
        //   150: aload           12
        //   152: ifnonnull       203
        //   155: new             Ljava/util/BitSet;
        //   158: dup            
        //   159: invokespecial   java/util/BitSet.<init>:()V
        //   162: astore          10
        //   164: aload           17
        //   166: iload           5
        //   168: invokestatic    java/lang/Integer.valueOf:(I)Ljava/lang/Integer;
        //   171: aload           10
        //   173: invokeinterface java/util/Map.put:(Ljava/lang/Object;Ljava/lang/Object;)Ljava/lang/Object;
        //   178: pop            
        //   179: new             Ljava/util/BitSet;
        //   182: dup            
        //   183: invokespecial   java/util/BitSet.<init>:()V
        //   186: astore          11
        //   188: aload           18
        //   190: iload           5
        //   192: invokestatic    java/lang/Integer.valueOf:(I)Ljava/lang/Integer;
        //   195: aload           11
        //   197: invokeinterface java/util/Map.put:(Ljava/lang/Object;Ljava/lang/Object;)Ljava/lang/Object;
        //   202: pop            
        //   203: iconst_0       
        //   204: istore          4
        //   206: iload           4
        //   208: aload           19
        //   210: getfield        com/google/android/gms/internal/zzcka.zzbwe:[J
        //   213: arraylength    
        //   214: bipush          6
        //   216: ishl           
        //   217: if_icmpge       292
        //   220: aload           19
        //   222: getfield        com/google/android/gms/internal/zzcka.zzbwe:[J
        //   225: iload           4
        //   227: invokestatic    com/google/android/gms/internal/zzcjl.zza:([JI)Z
        //   230: ifeq            283
        //   233: aload_0        
        //   234: invokevirtual   com/google/android/gms/internal/zzcej.zzwF:()Lcom/google/android/gms/internal/zzcfl;
        //   237: invokevirtual   com/google/android/gms/internal/zzcfl.zzyD:()Lcom/google/android/gms/internal/zzcfn;
        //   240: ldc_w           "Filter already evaluated. audience ID, filter ID"
        //   243: iload           5
        //   245: invokestatic    java/lang/Integer.valueOf:(I)Ljava/lang/Integer;
        //   248: iload           4
        //   250: invokestatic    java/lang/Integer.valueOf:(I)Ljava/lang/Integer;
        //   253: invokevirtual   com/google/android/gms/internal/zzcfn.zze:(Ljava/lang/String;Ljava/lang/Object;Ljava/lang/Object;)V
        //   256: aload           11
        //   258: iload           4
        //   260: invokevirtual   java/util/BitSet.set:(I)V
        //   263: aload           19
        //   265: getfield        com/google/android/gms/internal/zzcka.zzbwf:[J
        //   268: iload           4
        //   270: invokestatic    com/google/android/gms/internal/zzcjl.zza:([JI)Z
        //   273: ifeq            283
        //   276: aload           10
        //   278: iload           4
        //   280: invokevirtual   java/util/BitSet.set:(I)V
        //   283: iload           4
        //   285: iconst_1       
        //   286: iadd           
        //   287: istore          4
        //   289: goto            206
        //   292: new             Lcom/google/android/gms/internal/zzcjv;
        //   295: dup            
        //   296: invokespecial   com/google/android/gms/internal/zzcjv.<init>:()V
        //   299: astore          12
        //   301: aload           16
        //   303: iload           5
        //   305: invokestatic    java/lang/Integer.valueOf:(I)Ljava/lang/Integer;
        //   308: aload           12
        //   310: invokeinterface java/util/Map.put:(Ljava/lang/Object;Ljava/lang/Object;)Ljava/lang/Object;
        //   315: pop            
        //   316: aload           12
        //   318: iconst_0       
        //   319: invokestatic    java/lang/Boolean.valueOf:(Z)Ljava/lang/Boolean;
        //   322: putfield        com/google/android/gms/internal/zzcjv.zzbvu:Ljava/lang/Boolean;
        //   325: aload           12
        //   327: aload           19
        //   329: putfield        com/google/android/gms/internal/zzcjv.zzbvt:Lcom/google/android/gms/internal/zzcka;
        //   332: aload           12
        //   334: new             Lcom/google/android/gms/internal/zzcka;
        //   337: dup            
        //   338: invokespecial   com/google/android/gms/internal/zzcka.<init>:()V
        //   341: putfield        com/google/android/gms/internal/zzcjv.zzbvs:Lcom/google/android/gms/internal/zzcka;
        //   344: aload           12
        //   346: getfield        com/google/android/gms/internal/zzcjv.zzbvs:Lcom/google/android/gms/internal/zzcka;
        //   349: aload           10
        //   351: invokestatic    com/google/android/gms/internal/zzcjl.zza:(Ljava/util/BitSet;)[J
        //   354: putfield        com/google/android/gms/internal/zzcka.zzbwf:[J
        //   357: aload           12
        //   359: getfield        com/google/android/gms/internal/zzcjv.zzbvs:Lcom/google/android/gms/internal/zzcka;
        //   362: aload           11
        //   364: invokestatic    com/google/android/gms/internal/zzcjl.zza:(Ljava/util/BitSet;)[J
        //   367: putfield        com/google/android/gms/internal/zzcka.zzbwe:[J
        //   370: goto            70
        //   373: aload_2        
        //   374: ifnull          1107
        //   377: new             Landroid/support/v4/util/ArrayMap;
        //   380: dup            
        //   381: invokespecial   android/support/v4/util/ArrayMap.<init>:()V
        //   384: astore          19
        //   386: aload_2        
        //   387: arraylength    
        //   388: istore          5
        //   390: iconst_0       
        //   391: istore          4
        //   393: iload           4
        //   395: iload           5
        //   397: if_icmpge       1107
        //   400: aload_2        
        //   401: iload           4
        //   403: aaload         
        //   404: astore          20
        //   406: aload_0        
        //   407: invokevirtual   com/google/android/gms/internal/zzcej.zzwz:()Lcom/google/android/gms/internal/zzcen;
        //   410: aload_1        
        //   411: aload           20
        //   413: getfield        com/google/android/gms/internal/zzcjw.name:Ljava/lang/String;
        //   416: invokevirtual   com/google/android/gms/internal/zzcen.zzE:(Ljava/lang/String;Ljava/lang/String;)Lcom/google/android/gms/internal/zzcev;
        //   419: astore          10
        //   421: aload           10
        //   423: ifnonnull       641
        //   426: aload_0        
        //   427: invokevirtual   com/google/android/gms/internal/zzcej.zzwF:()Lcom/google/android/gms/internal/zzcfl;
        //   430: invokevirtual   com/google/android/gms/internal/zzcfl.zzyz:()Lcom/google/android/gms/internal/zzcfn;
        //   433: ldc_w           "Event aggregate wasn't created during raw event logging. appId, event"
        //   436: aload_1        
        //   437: invokestatic    com/google/android/gms/internal/zzcfl.zzdZ:(Ljava/lang/String;)Ljava/lang/Object;
        //   440: aload_0        
        //   441: invokevirtual   com/google/android/gms/internal/zzcej.zzwA:()Lcom/google/android/gms/internal/zzcfj;
        //   444: aload           20
        //   446: getfield        com/google/android/gms/internal/zzcjw.name:Ljava/lang/String;
        //   449: invokevirtual   com/google/android/gms/internal/zzcfj.zzdW:(Ljava/lang/String;)Ljava/lang/String;
        //   452: invokevirtual   com/google/android/gms/internal/zzcfn.zze:(Ljava/lang/String;Ljava/lang/Object;Ljava/lang/Object;)V
        //   455: new             Lcom/google/android/gms/internal/zzcev;
        //   458: dup            
        //   459: aload_1        
        //   460: aload           20
        //   462: getfield        com/google/android/gms/internal/zzcjw.name:Ljava/lang/String;
        //   465: lconst_1       
        //   466: lconst_1       
        //   467: aload           20
        //   469: getfield        com/google/android/gms/internal/zzcjw.zzbvx:Ljava/lang/Long;
        //   472: invokevirtual   java/lang/Long.longValue:()J
        //   475: invokespecial   com/google/android/gms/internal/zzcev.<init>:(Ljava/lang/String;Ljava/lang/String;JJJ)V
        //   478: astore          10
        //   480: aload_0        
        //   481: invokevirtual   com/google/android/gms/internal/zzcej.zzwz:()Lcom/google/android/gms/internal/zzcen;
        //   484: aload           10
        //   486: invokevirtual   com/google/android/gms/internal/zzcen.zza:(Lcom/google/android/gms/internal/zzcev;)V
        //   489: aload           10
        //   491: getfield        com/google/android/gms/internal/zzcev.zzbpG:J
        //   494: lstore          7
        //   496: aload           19
        //   498: aload           20
        //   500: getfield        com/google/android/gms/internal/zzcjw.name:Ljava/lang/String;
        //   503: invokeinterface java/util/Map.get:(Ljava/lang/Object;)Ljava/lang/Object;
        //   508: checkcast       Ljava/util/Map;
        //   511: astore          10
        //   513: aload           10
        //   515: ifnonnull       2488
        //   518: aload_0        
        //   519: invokevirtual   com/google/android/gms/internal/zzcej.zzwz:()Lcom/google/android/gms/internal/zzcen;
        //   522: aload_1        
        //   523: aload           20
        //   525: getfield        com/google/android/gms/internal/zzcjw.name:Ljava/lang/String;
        //   528: invokevirtual   com/google/android/gms/internal/zzcen.zzJ:(Ljava/lang/String;Ljava/lang/String;)Ljava/util/Map;
        //   531: astore          11
        //   533: aload           11
        //   535: astore          10
        //   537: aload           11
        //   539: ifnonnull       551
        //   542: new             Landroid/support/v4/util/ArrayMap;
        //   545: dup            
        //   546: invokespecial   android/support/v4/util/ArrayMap.<init>:()V
        //   549: astore          10
        //   551: aload           19
        //   553: aload           20
        //   555: getfield        com/google/android/gms/internal/zzcjw.name:Ljava/lang/String;
        //   558: aload           10
        //   560: invokeinterface java/util/Map.put:(Ljava/lang/Object;Ljava/lang/Object;)Ljava/lang/Object;
        //   565: pop            
        //   566: aload           10
        //   568: invokeinterface java/util/Map.keySet:()Ljava/util/Set;
        //   573: invokeinterface java/util/Set.iterator:()Ljava/util/Iterator;
        //   578: astore          21
        //   580: aload           21
        //   582: invokeinterface java/util/Iterator.hasNext:()Z
        //   587: ifeq            1098
        //   590: aload           21
        //   592: invokeinterface java/util/Iterator.next:()Ljava/lang/Object;
        //   597: checkcast       Ljava/lang/Integer;
        //   600: invokevirtual   java/lang/Integer.intValue:()I
        //   603: istore          6
        //   605: aload           15
        //   607: iload           6
        //   609: invokestatic    java/lang/Integer.valueOf:(I)Ljava/lang/Integer;
        //   612: invokeinterface java/util/Set.contains:(Ljava/lang/Object;)Z
        //   617: ifeq            651
        //   620: aload_0        
        //   621: invokevirtual   com/google/android/gms/internal/zzcej.zzwF:()Lcom/google/android/gms/internal/zzcfl;
        //   624: invokevirtual   com/google/android/gms/internal/zzcfl.zzyD:()Lcom/google/android/gms/internal/zzcfn;
        //   627: ldc_w           "Skipping failed audience ID"
        //   630: iload           6
        //   632: invokestatic    java/lang/Integer.valueOf:(I)Ljava/lang/Integer;
        //   635: invokevirtual   com/google/android/gms/internal/zzcfn.zzj:(Ljava/lang/String;Ljava/lang/Object;)V
        //   638: goto            580
        //   641: aload           10
        //   643: invokevirtual   com/google/android/gms/internal/zzcev.zzys:()Lcom/google/android/gms/internal/zzcev;
        //   646: astore          10
        //   648: goto            480
        //   651: aload           16
        //   653: iload           6
        //   655: invokestatic    java/lang/Integer.valueOf:(I)Ljava/lang/Integer;
        //   658: invokeinterface java/util/Map.get:(Ljava/lang/Object;)Ljava/lang/Object;
        //   663: checkcast       Lcom/google/android/gms/internal/zzcjv;
        //   666: astore          13
        //   668: aload           17
        //   670: iload           6
        //   672: invokestatic    java/lang/Integer.valueOf:(I)Ljava/lang/Integer;
        //   675: invokeinterface java/util/Map.get:(Ljava/lang/Object;)Ljava/lang/Object;
        //   680: checkcast       Ljava/util/BitSet;
        //   683: astore          11
        //   685: aload           18
        //   687: iload           6
        //   689: invokestatic    java/lang/Integer.valueOf:(I)Ljava/lang/Integer;
        //   692: invokeinterface java/util/Map.get:(Ljava/lang/Object;)Ljava/lang/Object;
        //   697: checkcast       Ljava/util/BitSet;
        //   700: astore          12
        //   702: aload           13
        //   704: ifnonnull       788
        //   707: new             Lcom/google/android/gms/internal/zzcjv;
        //   710: dup            
        //   711: invokespecial   com/google/android/gms/internal/zzcjv.<init>:()V
        //   714: astore          11
        //   716: aload           16
        //   718: iload           6
        //   720: invokestatic    java/lang/Integer.valueOf:(I)Ljava/lang/Integer;
        //   723: aload           11
        //   725: invokeinterface java/util/Map.put:(Ljava/lang/Object;Ljava/lang/Object;)Ljava/lang/Object;
        //   730: pop            
        //   731: aload           11
        //   733: iconst_1       
        //   734: invokestatic    java/lang/Boolean.valueOf:(Z)Ljava/lang/Boolean;
        //   737: putfield        com/google/android/gms/internal/zzcjv.zzbvu:Ljava/lang/Boolean;
        //   740: new             Ljava/util/BitSet;
        //   743: dup            
        //   744: invokespecial   java/util/BitSet.<init>:()V
        //   747: astore          11
        //   749: aload           17
        //   751: iload           6
        //   753: invokestatic    java/lang/Integer.valueOf:(I)Ljava/lang/Integer;
        //   756: aload           11
        //   758: invokeinterface java/util/Map.put:(Ljava/lang/Object;Ljava/lang/Object;)Ljava/lang/Object;
        //   763: pop            
        //   764: new             Ljava/util/BitSet;
        //   767: dup            
        //   768: invokespecial   java/util/BitSet.<init>:()V
        //   771: astore          12
        //   773: aload           18
        //   775: iload           6
        //   777: invokestatic    java/lang/Integer.valueOf:(I)Ljava/lang/Integer;
        //   780: aload           12
        //   782: invokeinterface java/util/Map.put:(Ljava/lang/Object;Ljava/lang/Object;)Ljava/lang/Object;
        //   787: pop            
        //   788: aload           10
        //   790: iload           6
        //   792: invokestatic    java/lang/Integer.valueOf:(I)Ljava/lang/Integer;
        //   795: invokeinterface java/util/Map.get:(Ljava/lang/Object;)Ljava/lang/Object;
        //   800: checkcast       Ljava/util/List;
        //   803: invokeinterface java/util/List.iterator:()Ljava/util/Iterator;
        //   808: astore          22
        //   810: aload           22
        //   812: invokeinterface java/util/Iterator.hasNext:()Z
        //   817: ifeq            580
        //   820: aload           22
        //   822: invokeinterface java/util/Iterator.next:()Ljava/lang/Object;
        //   827: checkcast       Lcom/google/android/gms/internal/zzcjn;
        //   830: astore          23
        //   832: aload_0        
        //   833: invokevirtual   com/google/android/gms/internal/zzcej.zzwF:()Lcom/google/android/gms/internal/zzcfl;
        //   836: iconst_2       
        //   837: invokevirtual   com/google/android/gms/internal/zzcfl.zzz:(I)Z
        //   840: ifeq            900
        //   843: aload_0        
        //   844: invokevirtual   com/google/android/gms/internal/zzcej.zzwF:()Lcom/google/android/gms/internal/zzcfl;
        //   847: invokevirtual   com/google/android/gms/internal/zzcfl.zzyD:()Lcom/google/android/gms/internal/zzcfn;
        //   850: ldc_w           "Evaluating filter. audience, filter, event"
        //   853: iload           6
        //   855: invokestatic    java/lang/Integer.valueOf:(I)Ljava/lang/Integer;
        //   858: aload           23
        //   860: getfield        com/google/android/gms/internal/zzcjn.zzbuM:Ljava/lang/Integer;
        //   863: aload_0        
        //   864: invokevirtual   com/google/android/gms/internal/zzcej.zzwA:()Lcom/google/android/gms/internal/zzcfj;
        //   867: aload           23
        //   869: getfield        com/google/android/gms/internal/zzcjn.zzbuN:Ljava/lang/String;
        //   872: invokevirtual   com/google/android/gms/internal/zzcfj.zzdW:(Ljava/lang/String;)Ljava/lang/String;
        //   875: invokevirtual   com/google/android/gms/internal/zzcfn.zzd:(Ljava/lang/String;Ljava/lang/Object;Ljava/lang/Object;Ljava/lang/Object;)V
        //   878: aload_0        
        //   879: invokevirtual   com/google/android/gms/internal/zzcej.zzwF:()Lcom/google/android/gms/internal/zzcfl;
        //   882: invokevirtual   com/google/android/gms/internal/zzcfl.zzyD:()Lcom/google/android/gms/internal/zzcfn;
        //   885: ldc_w           "Filter definition"
        //   888: aload_0        
        //   889: invokevirtual   com/google/android/gms/internal/zzcej.zzwA:()Lcom/google/android/gms/internal/zzcfj;
        //   892: aload           23
        //   894: invokevirtual   com/google/android/gms/internal/zzcfj.zza:(Lcom/google/android/gms/internal/zzcjn;)Ljava/lang/String;
        //   897: invokevirtual   com/google/android/gms/internal/zzcfn.zzj:(Ljava/lang/String;Ljava/lang/Object;)V
        //   900: aload           23
        //   902: getfield        com/google/android/gms/internal/zzcjn.zzbuM:Ljava/lang/Integer;
        //   905: ifnull          922
        //   908: aload           23
        //   910: getfield        com/google/android/gms/internal/zzcjn.zzbuM:Ljava/lang/Integer;
        //   913: invokevirtual   java/lang/Integer.intValue:()I
        //   916: sipush          256
        //   919: if_icmple       950
        //   922: aload_0        
        //   923: invokevirtual   com/google/android/gms/internal/zzcej.zzwF:()Lcom/google/android/gms/internal/zzcfl;
        //   926: invokevirtual   com/google/android/gms/internal/zzcfl.zzyz:()Lcom/google/android/gms/internal/zzcfn;
        //   929: ldc_w           "Invalid event filter ID. appId, id"
        //   932: aload_1        
        //   933: invokestatic    com/google/android/gms/internal/zzcfl.zzdZ:(Ljava/lang/String;)Ljava/lang/Object;
        //   936: aload           23
        //   938: getfield        com/google/android/gms/internal/zzcjn.zzbuM:Ljava/lang/Integer;
        //   941: invokestatic    java/lang/String.valueOf:(Ljava/lang/Object;)Ljava/lang/String;
        //   944: invokevirtual   com/google/android/gms/internal/zzcfn.zze:(Ljava/lang/String;Ljava/lang/Object;Ljava/lang/Object;)V
        //   947: goto            810
        //   950: aload           11
        //   952: aload           23
        //   954: getfield        com/google/android/gms/internal/zzcjn.zzbuM:Ljava/lang/Integer;
        //   957: invokevirtual   java/lang/Integer.intValue:()I
        //   960: invokevirtual   java/util/BitSet.get:(I)Z
        //   963: ifeq            992
        //   966: aload_0        
        //   967: invokevirtual   com/google/android/gms/internal/zzcej.zzwF:()Lcom/google/android/gms/internal/zzcfl;
        //   970: invokevirtual   com/google/android/gms/internal/zzcfl.zzyD:()Lcom/google/android/gms/internal/zzcfn;
        //   973: ldc_w           "Event filter already evaluated true. audience ID, filter ID"
        //   976: iload           6
        //   978: invokestatic    java/lang/Integer.valueOf:(I)Ljava/lang/Integer;
        //   981: aload           23
        //   983: getfield        com/google/android/gms/internal/zzcjn.zzbuM:Ljava/lang/Integer;
        //   986: invokevirtual   com/google/android/gms/internal/zzcfn.zze:(Ljava/lang/String;Ljava/lang/Object;Ljava/lang/Object;)V
        //   989: goto            810
        //   992: aload_0        
        //   993: aload           23
        //   995: aload           20
        //   997: lload           7
        //   999: invokespecial   com/google/android/gms/internal/zzcej.zza:(Lcom/google/android/gms/internal/zzcjn;Lcom/google/android/gms/internal/zzcjw;J)Ljava/lang/Boolean;
        //  1002: astore          14
        //  1004: aload_0        
        //  1005: invokevirtual   com/google/android/gms/internal/zzcej.zzwF:()Lcom/google/android/gms/internal/zzcfl;
        //  1008: invokevirtual   com/google/android/gms/internal/zzcfl.zzyD:()Lcom/google/android/gms/internal/zzcfn;
        //  1011: astore          24
        //  1013: aload           14
        //  1015: ifnonnull       1054
        //  1018: ldc_w           "null"
        //  1021: astore          13
        //  1023: aload           24
        //  1025: ldc_w           "Event filter result"
        //  1028: aload           13
        //  1030: invokevirtual   com/google/android/gms/internal/zzcfn.zzj:(Ljava/lang/String;Ljava/lang/Object;)V
        //  1033: aload           14
        //  1035: ifnonnull       1061
        //  1038: aload           15
        //  1040: iload           6
        //  1042: invokestatic    java/lang/Integer.valueOf:(I)Ljava/lang/Integer;
        //  1045: invokeinterface java/util/Set.add:(Ljava/lang/Object;)Z
        //  1050: pop            
        //  1051: goto            810
        //  1054: aload           14
        //  1056: astore          13
        //  1058: goto            1023
        //  1061: aload           12
        //  1063: aload           23
        //  1065: getfield        com/google/android/gms/internal/zzcjn.zzbuM:Ljava/lang/Integer;
        //  1068: invokevirtual   java/lang/Integer.intValue:()I
        //  1071: invokevirtual   java/util/BitSet.set:(I)V
        //  1074: aload           14
        //  1076: invokevirtual   java/lang/Boolean.booleanValue:()Z
        //  1079: ifeq            810
        //  1082: aload           11
        //  1084: aload           23
        //  1086: getfield        com/google/android/gms/internal/zzcjn.zzbuM:Ljava/lang/Integer;
        //  1089: invokevirtual   java/lang/Integer.intValue:()I
        //  1092: invokevirtual   java/util/BitSet.set:(I)V
        //  1095: goto            810
        //  1098: iload           4
        //  1100: iconst_1       
        //  1101: iadd           
        //  1102: istore          4
        //  1104: goto            393
        //  1107: aload_3        
        //  1108: ifnull          2092
        //  1111: new             Landroid/support/v4/util/ArrayMap;
        //  1114: dup            
        //  1115: invokespecial   android/support/v4/util/ArrayMap.<init>:()V
        //  1118: astore          14
        //  1120: aload_3        
        //  1121: arraylength    
        //  1122: istore          5
        //  1124: iconst_0       
        //  1125: istore          4
        //  1127: iload           4
        //  1129: iload           5
        //  1131: if_icmpge       2092
        //  1134: aload_3        
        //  1135: iload           4
        //  1137: aaload         
        //  1138: astore          19
        //  1140: aload           14
        //  1142: aload           19
        //  1144: getfield        com/google/android/gms/internal/zzckb.name:Ljava/lang/String;
        //  1147: invokeinterface java/util/Map.get:(Ljava/lang/Object;)Ljava/lang/Object;
        //  1152: checkcast       Ljava/util/Map;
        //  1155: astore          10
        //  1157: aload           10
        //  1159: ifnonnull       2485
        //  1162: aload_0        
        //  1163: invokevirtual   com/google/android/gms/internal/zzcej.zzwz:()Lcom/google/android/gms/internal/zzcen;
        //  1166: aload_1        
        //  1167: aload           19
        //  1169: getfield        com/google/android/gms/internal/zzckb.name:Ljava/lang/String;
        //  1172: invokevirtual   com/google/android/gms/internal/zzcen.zzK:(Ljava/lang/String;Ljava/lang/String;)Ljava/util/Map;
        //  1175: astore          10
        //  1177: aload           10
        //  1179: astore_2       
        //  1180: aload           10
        //  1182: ifnonnull       1193
        //  1185: new             Landroid/support/v4/util/ArrayMap;
        //  1188: dup            
        //  1189: invokespecial   android/support/v4/util/ArrayMap.<init>:()V
        //  1192: astore_2       
        //  1193: aload           14
        //  1195: aload           19
        //  1197: getfield        com/google/android/gms/internal/zzckb.name:Ljava/lang/String;
        //  1200: aload_2        
        //  1201: invokeinterface java/util/Map.put:(Ljava/lang/Object;Ljava/lang/Object;)Ljava/lang/Object;
        //  1206: pop            
        //  1207: aload_2        
        //  1208: astore          10
        //  1210: aload           10
        //  1212: invokeinterface java/util/Map.keySet:()Ljava/util/Set;
        //  1217: invokeinterface java/util/Set.iterator:()Ljava/util/Iterator;
        //  1222: astore          20
        //  1224: aload           20
        //  1226: invokeinterface java/util/Iterator.hasNext:()Z
        //  1231: ifeq            2083
        //  1234: aload           20
        //  1236: invokeinterface java/util/Iterator.next:()Ljava/lang/Object;
        //  1241: checkcast       Ljava/lang/Integer;
        //  1244: invokevirtual   java/lang/Integer.intValue:()I
        //  1247: istore          6
        //  1249: aload           15
        //  1251: iload           6
        //  1253: invokestatic    java/lang/Integer.valueOf:(I)Ljava/lang/Integer;
        //  1256: invokeinterface java/util/Set.contains:(Ljava/lang/Object;)Z
        //  1261: ifeq            1285
        //  1264: aload_0        
        //  1265: invokevirtual   com/google/android/gms/internal/zzcej.zzwF:()Lcom/google/android/gms/internal/zzcfl;
        //  1268: invokevirtual   com/google/android/gms/internal/zzcfl.zzyD:()Lcom/google/android/gms/internal/zzcfn;
        //  1271: ldc_w           "Skipping failed audience ID"
        //  1274: iload           6
        //  1276: invokestatic    java/lang/Integer.valueOf:(I)Ljava/lang/Integer;
        //  1279: invokevirtual   com/google/android/gms/internal/zzcfn.zzj:(Ljava/lang/String;Ljava/lang/Object;)V
        //  1282: goto            1224
        //  1285: aload           16
        //  1287: iload           6
        //  1289: invokestatic    java/lang/Integer.valueOf:(I)Ljava/lang/Integer;
        //  1292: invokeinterface java/util/Map.get:(Ljava/lang/Object;)Ljava/lang/Object;
        //  1297: checkcast       Lcom/google/android/gms/internal/zzcjv;
        //  1300: astore_2       
        //  1301: aload           17
        //  1303: iload           6
        //  1305: invokestatic    java/lang/Integer.valueOf:(I)Ljava/lang/Integer;
        //  1308: invokeinterface java/util/Map.get:(Ljava/lang/Object;)Ljava/lang/Object;
        //  1313: checkcast       Ljava/util/BitSet;
        //  1316: astore          11
        //  1318: aload           18
        //  1320: iload           6
        //  1322: invokestatic    java/lang/Integer.valueOf:(I)Ljava/lang/Integer;
        //  1325: invokeinterface java/util/Map.get:(Ljava/lang/Object;)Ljava/lang/Object;
        //  1330: checkcast       Ljava/util/BitSet;
        //  1333: astore          12
        //  1335: aload_2        
        //  1336: ifnonnull       1417
        //  1339: new             Lcom/google/android/gms/internal/zzcjv;
        //  1342: dup            
        //  1343: invokespecial   com/google/android/gms/internal/zzcjv.<init>:()V
        //  1346: astore_2       
        //  1347: aload           16
        //  1349: iload           6
        //  1351: invokestatic    java/lang/Integer.valueOf:(I)Ljava/lang/Integer;
        //  1354: aload_2        
        //  1355: invokeinterface java/util/Map.put:(Ljava/lang/Object;Ljava/lang/Object;)Ljava/lang/Object;
        //  1360: pop            
        //  1361: aload_2        
        //  1362: iconst_1       
        //  1363: invokestatic    java/lang/Boolean.valueOf:(Z)Ljava/lang/Boolean;
        //  1366: putfield        com/google/android/gms/internal/zzcjv.zzbvu:Ljava/lang/Boolean;
        //  1369: new             Ljava/util/BitSet;
        //  1372: dup            
        //  1373: invokespecial   java/util/BitSet.<init>:()V
        //  1376: astore          11
        //  1378: aload           17
        //  1380: iload           6
        //  1382: invokestatic    java/lang/Integer.valueOf:(I)Ljava/lang/Integer;
        //  1385: aload           11
        //  1387: invokeinterface java/util/Map.put:(Ljava/lang/Object;Ljava/lang/Object;)Ljava/lang/Object;
        //  1392: pop            
        //  1393: new             Ljava/util/BitSet;
        //  1396: dup            
        //  1397: invokespecial   java/util/BitSet.<init>:()V
        //  1400: astore          12
        //  1402: aload           18
        //  1404: iload           6
        //  1406: invokestatic    java/lang/Integer.valueOf:(I)Ljava/lang/Integer;
        //  1409: aload           12
        //  1411: invokeinterface java/util/Map.put:(Ljava/lang/Object;Ljava/lang/Object;)Ljava/lang/Object;
        //  1416: pop            
        //  1417: aload           10
        //  1419: iload           6
        //  1421: invokestatic    java/lang/Integer.valueOf:(I)Ljava/lang/Integer;
        //  1424: invokeinterface java/util/Map.get:(Ljava/lang/Object;)Ljava/lang/Object;
        //  1429: checkcast       Ljava/util/List;
        //  1432: invokeinterface java/util/List.iterator:()Ljava/util/Iterator;
        //  1437: astore          21
        //  1439: aload           21
        //  1441: invokeinterface java/util/Iterator.hasNext:()Z
        //  1446: ifeq            1224
        //  1449: aload           21
        //  1451: invokeinterface java/util/Iterator.next:()Ljava/lang/Object;
        //  1456: checkcast       Lcom/google/android/gms/internal/zzcjq;
        //  1459: astore          22
        //  1461: aload_0        
        //  1462: invokevirtual   com/google/android/gms/internal/zzcej.zzwF:()Lcom/google/android/gms/internal/zzcfl;
        //  1465: iconst_2       
        //  1466: invokevirtual   com/google/android/gms/internal/zzcfl.zzz:(I)Z
        //  1469: ifeq            1529
        //  1472: aload_0        
        //  1473: invokevirtual   com/google/android/gms/internal/zzcej.zzwF:()Lcom/google/android/gms/internal/zzcfl;
        //  1476: invokevirtual   com/google/android/gms/internal/zzcfl.zzyD:()Lcom/google/android/gms/internal/zzcfn;
        //  1479: ldc_w           "Evaluating filter. audience, filter, property"
        //  1482: iload           6
        //  1484: invokestatic    java/lang/Integer.valueOf:(I)Ljava/lang/Integer;
        //  1487: aload           22
        //  1489: getfield        com/google/android/gms/internal/zzcjq.zzbuM:Ljava/lang/Integer;
        //  1492: aload_0        
        //  1493: invokevirtual   com/google/android/gms/internal/zzcej.zzwA:()Lcom/google/android/gms/internal/zzcfj;
        //  1496: aload           22
        //  1498: getfield        com/google/android/gms/internal/zzcjq.zzbvc:Ljava/lang/String;
        //  1501: invokevirtual   com/google/android/gms/internal/zzcfj.zzdY:(Ljava/lang/String;)Ljava/lang/String;
        //  1504: invokevirtual   com/google/android/gms/internal/zzcfn.zzd:(Ljava/lang/String;Ljava/lang/Object;Ljava/lang/Object;Ljava/lang/Object;)V
        //  1507: aload_0        
        //  1508: invokevirtual   com/google/android/gms/internal/zzcej.zzwF:()Lcom/google/android/gms/internal/zzcfl;
        //  1511: invokevirtual   com/google/android/gms/internal/zzcfl.zzyD:()Lcom/google/android/gms/internal/zzcfn;
        //  1514: ldc_w           "Filter definition"
        //  1517: aload_0        
        //  1518: invokevirtual   com/google/android/gms/internal/zzcej.zzwA:()Lcom/google/android/gms/internal/zzcfj;
        //  1521: aload           22
        //  1523: invokevirtual   com/google/android/gms/internal/zzcfj.zza:(Lcom/google/android/gms/internal/zzcjq;)Ljava/lang/String;
        //  1526: invokevirtual   com/google/android/gms/internal/zzcfn.zzj:(Ljava/lang/String;Ljava/lang/Object;)V
        //  1529: aload           22
        //  1531: getfield        com/google/android/gms/internal/zzcjq.zzbuM:Ljava/lang/Integer;
        //  1534: ifnull          1551
        //  1537: aload           22
        //  1539: getfield        com/google/android/gms/internal/zzcjq.zzbuM:Ljava/lang/Integer;
        //  1542: invokevirtual   java/lang/Integer.intValue:()I
        //  1545: sipush          256
        //  1548: if_icmple       1592
        //  1551: aload_0        
        //  1552: invokevirtual   com/google/android/gms/internal/zzcej.zzwF:()Lcom/google/android/gms/internal/zzcfl;
        //  1555: invokevirtual   com/google/android/gms/internal/zzcfl.zzyz:()Lcom/google/android/gms/internal/zzcfn;
        //  1558: ldc_w           "Invalid property filter ID. appId, id"
        //  1561: aload_1        
        //  1562: invokestatic    com/google/android/gms/internal/zzcfl.zzdZ:(Ljava/lang/String;)Ljava/lang/Object;
        //  1565: aload           22
        //  1567: getfield        com/google/android/gms/internal/zzcjq.zzbuM:Ljava/lang/Integer;
        //  1570: invokestatic    java/lang/String.valueOf:(Ljava/lang/Object;)Ljava/lang/String;
        //  1573: invokevirtual   com/google/android/gms/internal/zzcfn.zze:(Ljava/lang/String;Ljava/lang/Object;Ljava/lang/Object;)V
        //  1576: aload           15
        //  1578: iload           6
        //  1580: invokestatic    java/lang/Integer.valueOf:(I)Ljava/lang/Integer;
        //  1583: invokeinterface java/util/Set.add:(Ljava/lang/Object;)Z
        //  1588: pop            
        //  1589: goto            1224
        //  1592: aload           11
        //  1594: aload           22
        //  1596: getfield        com/google/android/gms/internal/zzcjq.zzbuM:Ljava/lang/Integer;
        //  1599: invokevirtual   java/lang/Integer.intValue:()I
        //  1602: invokevirtual   java/util/BitSet.get:(I)Z
        //  1605: ifeq            1634
        //  1608: aload_0        
        //  1609: invokevirtual   com/google/android/gms/internal/zzcej.zzwF:()Lcom/google/android/gms/internal/zzcfl;
        //  1612: invokevirtual   com/google/android/gms/internal/zzcfl.zzyD:()Lcom/google/android/gms/internal/zzcfn;
        //  1615: ldc_w           "Property filter already evaluated true. audience ID, filter ID"
        //  1618: iload           6
        //  1620: invokestatic    java/lang/Integer.valueOf:(I)Ljava/lang/Integer;
        //  1623: aload           22
        //  1625: getfield        com/google/android/gms/internal/zzcjq.zzbuM:Ljava/lang/Integer;
        //  1628: invokevirtual   com/google/android/gms/internal/zzcfn.zze:(Ljava/lang/String;Ljava/lang/Object;Ljava/lang/Object;)V
        //  1631: goto            1439
        //  1634: aload           22
        //  1636: getfield        com/google/android/gms/internal/zzcjq.zzbvd:Lcom/google/android/gms/internal/zzcjo;
        //  1639: astore_2       
        //  1640: aload_2        
        //  1641: ifnonnull       1719
        //  1644: aload_0        
        //  1645: invokevirtual   com/google/android/gms/internal/zzcej.zzwF:()Lcom/google/android/gms/internal/zzcfl;
        //  1648: invokevirtual   com/google/android/gms/internal/zzcfl.zzyz:()Lcom/google/android/gms/internal/zzcfn;
        //  1651: ldc_w           "Missing property filter. property"
        //  1654: aload_0        
        //  1655: invokevirtual   com/google/android/gms/internal/zzcej.zzwA:()Lcom/google/android/gms/internal/zzcfj;
        //  1658: aload           19
        //  1660: getfield        com/google/android/gms/internal/zzckb.name:Ljava/lang/String;
        //  1663: invokevirtual   com/google/android/gms/internal/zzcfj.zzdY:(Ljava/lang/String;)Ljava/lang/String;
        //  1666: invokevirtual   com/google/android/gms/internal/zzcfn.zzj:(Ljava/lang/String;Ljava/lang/Object;)V
        //  1669: aconst_null    
        //  1670: astore_2       
        //  1671: aload_0        
        //  1672: invokevirtual   com/google/android/gms/internal/zzcej.zzwF:()Lcom/google/android/gms/internal/zzcfl;
        //  1675: invokevirtual   com/google/android/gms/internal/zzcfl.zzyD:()Lcom/google/android/gms/internal/zzcfn;
        //  1678: astore          23
        //  1680: aload_2        
        //  1681: ifnonnull       2041
        //  1684: ldc_w           "null"
        //  1687: astore          13
        //  1689: aload           23
        //  1691: ldc_w           "Property filter result"
        //  1694: aload           13
        //  1696: invokevirtual   com/google/android/gms/internal/zzcfn.zzj:(Ljava/lang/String;Ljava/lang/Object;)V
        //  1699: aload_2        
        //  1700: ifnonnull       2047
        //  1703: aload           15
        //  1705: iload           6
        //  1707: invokestatic    java/lang/Integer.valueOf:(I)Ljava/lang/Integer;
        //  1710: invokeinterface java/util/Set.add:(Ljava/lang/Object;)Z
        //  1715: pop            
        //  1716: goto            1439
        //  1719: getstatic       java/lang/Boolean.TRUE:Ljava/lang/Boolean;
        //  1722: aload_2        
        //  1723: getfield        com/google/android/gms/internal/zzcjo.zzbuU:Ljava/lang/Boolean;
        //  1726: invokevirtual   java/lang/Boolean.equals:(Ljava/lang/Object;)Z
        //  1729: istore          9
        //  1731: aload           19
        //  1733: getfield        com/google/android/gms/internal/zzckb.zzbvA:Ljava/lang/Long;
        //  1736: ifnull          1801
        //  1739: aload_2        
        //  1740: getfield        com/google/android/gms/internal/zzcjo.zzbuT:Lcom/google/android/gms/internal/zzcjp;
        //  1743: ifnonnull       1776
        //  1746: aload_0        
        //  1747: invokevirtual   com/google/android/gms/internal/zzcej.zzwF:()Lcom/google/android/gms/internal/zzcfl;
        //  1750: invokevirtual   com/google/android/gms/internal/zzcfl.zzyz:()Lcom/google/android/gms/internal/zzcfn;
        //  1753: ldc_w           "No number filter for long property. property"
        //  1756: aload_0        
        //  1757: invokevirtual   com/google/android/gms/internal/zzcej.zzwA:()Lcom/google/android/gms/internal/zzcfj;
        //  1760: aload           19
        //  1762: getfield        com/google/android/gms/internal/zzckb.name:Ljava/lang/String;
        //  1765: invokevirtual   com/google/android/gms/internal/zzcfj.zzdY:(Ljava/lang/String;)Ljava/lang/String;
        //  1768: invokevirtual   com/google/android/gms/internal/zzcfn.zzj:(Ljava/lang/String;Ljava/lang/Object;)V
        //  1771: aconst_null    
        //  1772: astore_2       
        //  1773: goto            1671
        //  1776: aload_0        
        //  1777: aload           19
        //  1779: getfield        com/google/android/gms/internal/zzckb.zzbvA:Ljava/lang/Long;
        //  1782: invokevirtual   java/lang/Long.longValue:()J
        //  1785: aload_2        
        //  1786: getfield        com/google/android/gms/internal/zzcjo.zzbuT:Lcom/google/android/gms/internal/zzcjp;
        //  1789: invokespecial   com/google/android/gms/internal/zzcej.zza:(JLcom/google/android/gms/internal/zzcjp;)Ljava/lang/Boolean;
        //  1792: iload           9
        //  1794: invokestatic    com/google/android/gms/internal/zzcej.zza:(Ljava/lang/Boolean;Z)Ljava/lang/Boolean;
        //  1797: astore_2       
        //  1798: goto            1671
        //  1801: aload           19
        //  1803: getfield        com/google/android/gms/internal/zzckb.zzbuB:Ljava/lang/Double;
        //  1806: ifnull          1871
        //  1809: aload_2        
        //  1810: getfield        com/google/android/gms/internal/zzcjo.zzbuT:Lcom/google/android/gms/internal/zzcjp;
        //  1813: ifnonnull       1846
        //  1816: aload_0        
        //  1817: invokevirtual   com/google/android/gms/internal/zzcej.zzwF:()Lcom/google/android/gms/internal/zzcfl;
        //  1820: invokevirtual   com/google/android/gms/internal/zzcfl.zzyz:()Lcom/google/android/gms/internal/zzcfn;
        //  1823: ldc_w           "No number filter for double property. property"
        //  1826: aload_0        
        //  1827: invokevirtual   com/google/android/gms/internal/zzcej.zzwA:()Lcom/google/android/gms/internal/zzcfj;
        //  1830: aload           19
        //  1832: getfield        com/google/android/gms/internal/zzckb.name:Ljava/lang/String;
        //  1835: invokevirtual   com/google/android/gms/internal/zzcfj.zzdY:(Ljava/lang/String;)Ljava/lang/String;
        //  1838: invokevirtual   com/google/android/gms/internal/zzcfn.zzj:(Ljava/lang/String;Ljava/lang/Object;)V
        //  1841: aconst_null    
        //  1842: astore_2       
        //  1843: goto            1671
        //  1846: aload_0        
        //  1847: aload           19
        //  1849: getfield        com/google/android/gms/internal/zzckb.zzbuB:Ljava/lang/Double;
        //  1852: invokevirtual   java/lang/Double.doubleValue:()D
        //  1855: aload_2        
        //  1856: getfield        com/google/android/gms/internal/zzcjo.zzbuT:Lcom/google/android/gms/internal/zzcjp;
        //  1859: invokespecial   com/google/android/gms/internal/zzcej.zza:(DLcom/google/android/gms/internal/zzcjp;)Ljava/lang/Boolean;
        //  1862: iload           9
        //  1864: invokestatic    com/google/android/gms/internal/zzcej.zza:(Ljava/lang/Boolean;Z)Ljava/lang/Boolean;
        //  1867: astore_2       
        //  1868: goto            1671
        //  1871: aload           19
        //  1873: getfield        com/google/android/gms/internal/zzckb.zzaIF:Ljava/lang/String;
        //  1876: ifnull          2011
        //  1879: aload_2        
        //  1880: getfield        com/google/android/gms/internal/zzcjo.zzbuS:Lcom/google/android/gms/internal/zzcjr;
        //  1883: ifnonnull       1989
        //  1886: aload_2        
        //  1887: getfield        com/google/android/gms/internal/zzcjo.zzbuT:Lcom/google/android/gms/internal/zzcjp;
        //  1890: ifnonnull       1923
        //  1893: aload_0        
        //  1894: invokevirtual   com/google/android/gms/internal/zzcej.zzwF:()Lcom/google/android/gms/internal/zzcfl;
        //  1897: invokevirtual   com/google/android/gms/internal/zzcfl.zzyz:()Lcom/google/android/gms/internal/zzcfn;
        //  1900: ldc_w           "No string or number filter defined. property"
        //  1903: aload_0        
        //  1904: invokevirtual   com/google/android/gms/internal/zzcej.zzwA:()Lcom/google/android/gms/internal/zzcfj;
        //  1907: aload           19
        //  1909: getfield        com/google/android/gms/internal/zzckb.name:Ljava/lang/String;
        //  1912: invokevirtual   com/google/android/gms/internal/zzcfj.zzdY:(Ljava/lang/String;)Ljava/lang/String;
        //  1915: invokevirtual   com/google/android/gms/internal/zzcfn.zzj:(Ljava/lang/String;Ljava/lang/Object;)V
        //  1918: aconst_null    
        //  1919: astore_2       
        //  1920: goto            1671
        //  1923: aload           19
        //  1925: getfield        com/google/android/gms/internal/zzckb.zzaIF:Ljava/lang/String;
        //  1928: invokestatic    com/google/android/gms/internal/zzcjl.zzez:(Ljava/lang/String;)Z
        //  1931: ifeq            1956
        //  1934: aload_0        
        //  1935: aload           19
        //  1937: getfield        com/google/android/gms/internal/zzckb.zzaIF:Ljava/lang/String;
        //  1940: aload_2        
        //  1941: getfield        com/google/android/gms/internal/zzcjo.zzbuT:Lcom/google/android/gms/internal/zzcjp;
        //  1944: invokespecial   com/google/android/gms/internal/zzcej.zza:(Ljava/lang/String;Lcom/google/android/gms/internal/zzcjp;)Ljava/lang/Boolean;
        //  1947: iload           9
        //  1949: invokestatic    com/google/android/gms/internal/zzcej.zza:(Ljava/lang/Boolean;Z)Ljava/lang/Boolean;
        //  1952: astore_2       
        //  1953: goto            1671
        //  1956: aload_0        
        //  1957: invokevirtual   com/google/android/gms/internal/zzcej.zzwF:()Lcom/google/android/gms/internal/zzcfl;
        //  1960: invokevirtual   com/google/android/gms/internal/zzcfl.zzyz:()Lcom/google/android/gms/internal/zzcfn;
        //  1963: ldc_w           "Invalid user property value for Numeric number filter. property, value"
        //  1966: aload_0        
        //  1967: invokevirtual   com/google/android/gms/internal/zzcej.zzwA:()Lcom/google/android/gms/internal/zzcfj;
        //  1970: aload           19
        //  1972: getfield        com/google/android/gms/internal/zzckb.name:Ljava/lang/String;
        //  1975: invokevirtual   com/google/android/gms/internal/zzcfj.zzdY:(Ljava/lang/String;)Ljava/lang/String;
        //  1978: aload           19
        //  1980: getfield        com/google/android/gms/internal/zzckb.zzaIF:Ljava/lang/String;
        //  1983: invokevirtual   com/google/android/gms/internal/zzcfn.zze:(Ljava/lang/String;Ljava/lang/Object;Ljava/lang/Object;)V
        //  1986: goto            1918
        //  1989: aload_0        
        //  1990: aload           19
        //  1992: getfield        com/google/android/gms/internal/zzckb.zzaIF:Ljava/lang/String;
        //  1995: aload_2        
        //  1996: getfield        com/google/android/gms/internal/zzcjo.zzbuS:Lcom/google/android/gms/internal/zzcjr;
        //  1999: invokespecial   com/google/android/gms/internal/zzcej.zza:(Ljava/lang/String;Lcom/google/android/gms/internal/zzcjr;)Ljava/lang/Boolean;
        //  2002: iload           9
        //  2004: invokestatic    com/google/android/gms/internal/zzcej.zza:(Ljava/lang/Boolean;Z)Ljava/lang/Boolean;
        //  2007: astore_2       
        //  2008: goto            1671
        //  2011: aload_0        
        //  2012: invokevirtual   com/google/android/gms/internal/zzcej.zzwF:()Lcom/google/android/gms/internal/zzcfl;
        //  2015: invokevirtual   com/google/android/gms/internal/zzcfl.zzyz:()Lcom/google/android/gms/internal/zzcfn;
        //  2018: ldc_w           "User property has no value, property"
        //  2021: aload_0        
        //  2022: invokevirtual   com/google/android/gms/internal/zzcej.zzwA:()Lcom/google/android/gms/internal/zzcfj;
        //  2025: aload           19
        //  2027: getfield        com/google/android/gms/internal/zzckb.name:Ljava/lang/String;
        //  2030: invokevirtual   com/google/android/gms/internal/zzcfj.zzdY:(Ljava/lang/String;)Ljava/lang/String;
        //  2033: invokevirtual   com/google/android/gms/internal/zzcfn.zzj:(Ljava/lang/String;Ljava/lang/Object;)V
        //  2036: aconst_null    
        //  2037: astore_2       
        //  2038: goto            1671
        //  2041: aload_2        
        //  2042: astore          13
        //  2044: goto            1689
        //  2047: aload           12
        //  2049: aload           22
        //  2051: getfield        com/google/android/gms/internal/zzcjq.zzbuM:Ljava/lang/Integer;
        //  2054: invokevirtual   java/lang/Integer.intValue:()I
        //  2057: invokevirtual   java/util/BitSet.set:(I)V
        //  2060: aload_2        
        //  2061: invokevirtual   java/lang/Boolean.booleanValue:()Z
        //  2064: ifeq            1439
        //  2067: aload           11
        //  2069: aload           22
        //  2071: getfield        com/google/android/gms/internal/zzcjq.zzbuM:Ljava/lang/Integer;
        //  2074: invokevirtual   java/lang/Integer.intValue:()I
        //  2077: invokevirtual   java/util/BitSet.set:(I)V
        //  2080: goto            1439
        //  2083: iload           4
        //  2085: iconst_1       
        //  2086: iadd           
        //  2087: istore          4
        //  2089: goto            1127
        //  2092: aload           17
        //  2094: invokeinterface java/util/Map.size:()I
        //  2099: anewarray       Lcom/google/android/gms/internal/zzcjv;
        //  2102: astore_3       
        //  2103: aload           17
        //  2105: invokeinterface java/util/Map.keySet:()Ljava/util/Set;
        //  2110: invokeinterface java/util/Set.iterator:()Ljava/util/Iterator;
        //  2115: astore          10
        //  2117: iconst_0       
        //  2118: istore          4
        //  2120: aload           10
        //  2122: invokeinterface java/util/Iterator.hasNext:()Z
        //  2127: ifeq            2472
        //  2130: aload           10
        //  2132: invokeinterface java/util/Iterator.next:()Ljava/lang/Object;
        //  2137: checkcast       Ljava/lang/Integer;
        //  2140: invokevirtual   java/lang/Integer.intValue:()I
        //  2143: istore          6
        //  2145: aload           15
        //  2147: iload           6
        //  2149: invokestatic    java/lang/Integer.valueOf:(I)Ljava/lang/Integer;
        //  2152: invokeinterface java/util/Set.contains:(Ljava/lang/Object;)Z
        //  2157: ifne            2120
        //  2160: aload           16
        //  2162: iload           6
        //  2164: invokestatic    java/lang/Integer.valueOf:(I)Ljava/lang/Integer;
        //  2167: invokeinterface java/util/Map.get:(Ljava/lang/Object;)Ljava/lang/Object;
        //  2172: checkcast       Lcom/google/android/gms/internal/zzcjv;
        //  2175: astore_2       
        //  2176: aload_2        
        //  2177: ifnonnull       2482
        //  2180: new             Lcom/google/android/gms/internal/zzcjv;
        //  2183: dup            
        //  2184: invokespecial   com/google/android/gms/internal/zzcjv.<init>:()V
        //  2187: astore_2       
        //  2188: iload           4
        //  2190: iconst_1       
        //  2191: iadd           
        //  2192: istore          5
        //  2194: aload_3        
        //  2195: iload           4
        //  2197: aload_2        
        //  2198: aastore        
        //  2199: aload_2        
        //  2200: iload           6
        //  2202: invokestatic    java/lang/Integer.valueOf:(I)Ljava/lang/Integer;
        //  2205: putfield        com/google/android/gms/internal/zzcjv.zzbuI:Ljava/lang/Integer;
        //  2208: aload_2        
        //  2209: new             Lcom/google/android/gms/internal/zzcka;
        //  2212: dup            
        //  2213: invokespecial   com/google/android/gms/internal/zzcka.<init>:()V
        //  2216: putfield        com/google/android/gms/internal/zzcjv.zzbvs:Lcom/google/android/gms/internal/zzcka;
        //  2219: aload_2        
        //  2220: getfield        com/google/android/gms/internal/zzcjv.zzbvs:Lcom/google/android/gms/internal/zzcka;
        //  2223: aload           17
        //  2225: iload           6
        //  2227: invokestatic    java/lang/Integer.valueOf:(I)Ljava/lang/Integer;
        //  2230: invokeinterface java/util/Map.get:(Ljava/lang/Object;)Ljava/lang/Object;
        //  2235: checkcast       Ljava/util/BitSet;
        //  2238: invokestatic    com/google/android/gms/internal/zzcjl.zza:(Ljava/util/BitSet;)[J
        //  2241: putfield        com/google/android/gms/internal/zzcka.zzbwf:[J
        //  2244: aload_2        
        //  2245: getfield        com/google/android/gms/internal/zzcjv.zzbvs:Lcom/google/android/gms/internal/zzcka;
        //  2248: aload           18
        //  2250: iload           6
        //  2252: invokestatic    java/lang/Integer.valueOf:(I)Ljava/lang/Integer;
        //  2255: invokeinterface java/util/Map.get:(Ljava/lang/Object;)Ljava/lang/Object;
        //  2260: checkcast       Ljava/util/BitSet;
        //  2263: invokestatic    com/google/android/gms/internal/zzcjl.zza:(Ljava/util/BitSet;)[J
        //  2266: putfield        com/google/android/gms/internal/zzcka.zzbwe:[J
        //  2269: aload_0        
        //  2270: invokevirtual   com/google/android/gms/internal/zzcej.zzwz:()Lcom/google/android/gms/internal/zzcen;
        //  2273: astore          11
        //  2275: aload_2        
        //  2276: getfield        com/google/android/gms/internal/zzcjv.zzbvs:Lcom/google/android/gms/internal/zzcka;
        //  2279: astore          12
        //  2281: aload           11
        //  2283: invokevirtual   com/google/android/gms/internal/zzcen.zzkD:()V
        //  2286: aload           11
        //  2288: invokevirtual   com/google/android/gms/internal/zzcen.zzjC:()V
        //  2291: aload_1        
        //  2292: invokestatic    com/google/android/gms/common/internal/zzbo.zzcF:(Ljava/lang/String;)Ljava/lang/String;
        //  2295: pop            
        //  2296: aload           12
        //  2298: invokestatic    com/google/android/gms/common/internal/zzbo.zzu:(Ljava/lang/Object;)Ljava/lang/Object;
        //  2301: pop            
        //  2302: aload           12
        //  2304: invokevirtual   com/google/android/gms/internal/zzcka.zzLV:()I
        //  2307: newarray        B
        //  2309: astore_2       
        //  2310: aload_2        
        //  2311: iconst_0       
        //  2312: aload_2        
        //  2313: arraylength    
        //  2314: invokestatic    com/google/android/gms/internal/adh.zzc:([BII)Lcom/google/android/gms/internal/adh;
        //  2317: astore          13
        //  2319: aload           12
        //  2321: aload           13
        //  2323: invokevirtual   com/google/android/gms/internal/zzcka.zza:(Lcom/google/android/gms/internal/adh;)V
        //  2326: aload           13
        //  2328: invokevirtual   com/google/android/gms/internal/adh.zzLM:()V
        //  2331: new             Landroid/content/ContentValues;
        //  2334: dup            
        //  2335: invokespecial   android/content/ContentValues.<init>:()V
        //  2338: astore          12
        //  2340: aload           12
        //  2342: ldc_w           "app_id"
        //  2345: aload_1        
        //  2346: invokevirtual   android/content/ContentValues.put:(Ljava/lang/String;Ljava/lang/String;)V
        //  2349: aload           12
        //  2351: ldc_w           "audience_id"
        //  2354: iload           6
        //  2356: invokestatic    java/lang/Integer.valueOf:(I)Ljava/lang/Integer;
        //  2359: invokevirtual   android/content/ContentValues.put:(Ljava/lang/String;Ljava/lang/Integer;)V
        //  2362: aload           12
        //  2364: ldc_w           "current_results"
        //  2367: aload_2        
        //  2368: invokevirtual   android/content/ContentValues.put:(Ljava/lang/String;[B)V
        //  2371: aload           11
        //  2373: invokevirtual   com/google/android/gms/internal/zzcen.getWritableDatabase:()Landroid/database/sqlite/SQLiteDatabase;
        //  2376: ldc_w           "audience_filter_values"
        //  2379: aconst_null    
        //  2380: aload           12
        //  2382: iconst_5       
        //  2383: invokevirtual   android/database/sqlite/SQLiteDatabase.insertWithOnConflict:(Ljava/lang/String;Ljava/lang/String;Landroid/content/ContentValues;I)J
        //  2386: ldc2_w          -1
        //  2389: lcmp           
        //  2390: ifne            2411
        //  2393: aload           11
        //  2395: invokevirtual   com/google/android/gms/internal/zzcen.zzwF:()Lcom/google/android/gms/internal/zzcfl;
        //  2398: invokevirtual   com/google/android/gms/internal/zzcfl.zzyx:()Lcom/google/android/gms/internal/zzcfn;
        //  2401: ldc_w           "Failed to insert filter results (got -1). appId"
        //  2404: aload_1        
        //  2405: invokestatic    com/google/android/gms/internal/zzcfl.zzdZ:(Ljava/lang/String;)Ljava/lang/Object;
        //  2408: invokevirtual   com/google/android/gms/internal/zzcfn.zzj:(Ljava/lang/String;Ljava/lang/Object;)V
        //  2411: iload           5
        //  2413: istore          4
        //  2415: goto            2120
        //  2418: astore_2       
        //  2419: aload           11
        //  2421: invokevirtual   com/google/android/gms/internal/zzcen.zzwF:()Lcom/google/android/gms/internal/zzcfl;
        //  2424: invokevirtual   com/google/android/gms/internal/zzcfl.zzyx:()Lcom/google/android/gms/internal/zzcfn;
        //  2427: ldc_w           "Configuration loss. Failed to serialize filter results. appId"
        //  2430: aload_1        
        //  2431: invokestatic    com/google/android/gms/internal/zzcfl.zzdZ:(Ljava/lang/String;)Ljava/lang/Object;
        //  2434: aload_2        
        //  2435: invokevirtual   com/google/android/gms/internal/zzcfn.zze:(Ljava/lang/String;Ljava/lang/Object;Ljava/lang/Object;)V
        //  2438: iload           5
        //  2440: istore          4
        //  2442: goto            2120
        //  2445: astore_2       
        //  2446: aload           11
        //  2448: invokevirtual   com/google/android/gms/internal/zzcen.zzwF:()Lcom/google/android/gms/internal/zzcfl;
        //  2451: invokevirtual   com/google/android/gms/internal/zzcfl.zzyx:()Lcom/google/android/gms/internal/zzcfn;
        //  2454: ldc_w           "Error storing filter results. appId"
        //  2457: aload_1        
        //  2458: invokestatic    com/google/android/gms/internal/zzcfl.zzdZ:(Ljava/lang/String;)Ljava/lang/Object;
        //  2461: aload_2        
        //  2462: invokevirtual   com/google/android/gms/internal/zzcfn.zze:(Ljava/lang/String;Ljava/lang/Object;Ljava/lang/Object;)V
        //  2465: iload           5
        //  2467: istore          4
        //  2469: goto            2120
        //  2472: aload_3        
        //  2473: iload           4
        //  2475: invokestatic    java/util/Arrays.copyOf:([Ljava/lang/Object;I)[Ljava/lang/Object;
        //  2478: checkcast       [Lcom/google/android/gms/internal/zzcjv;
        //  2481: areturn        
        //  2482: goto            2188
        //  2485: goto            1210
        //  2488: goto            566
        //    Exceptions:
        //  Try           Handler
        //  Start  End    Start  End    Type                                     
        //  -----  -----  -----  -----  -----------------------------------------
        //  2302   2331   2418   2445   Ljava/io/IOException;
        //  2371   2411   2445   2472   Landroid/database/sqlite/SQLiteException;
        // 
        // The error that occurred was:
        // 
        // java.lang.IllegalStateException: Expression is linked from several locations: Label_2411:
        //     at com.strobel.decompiler.ast.Error.expressionLinkedFromMultipleLocations(Error.java:27)
        //     at com.strobel.decompiler.ast.AstOptimizer.mergeDisparateObjectInitializations(AstOptimizer.java:2596)
        //     at com.strobel.decompiler.ast.AstOptimizer.optimize(AstOptimizer.java:235)
        //     at com.strobel.decompiler.ast.AstOptimizer.optimize(AstOptimizer.java:42)
        //     at com.strobel.decompiler.languages.java.ast.AstMethodBodyBuilder.createMethodBody(AstMethodBodyBuilder.java:214)
        //     at com.strobel.decompiler.languages.java.ast.AstMethodBodyBuilder.createMethodBody(AstMethodBodyBuilder.java:99)
        //     at com.strobel.decompiler.languages.java.ast.AstBuilder.createMethodBody(AstBuilder.java:782)
        //     at com.strobel.decompiler.languages.java.ast.AstBuilder.createMethod(AstBuilder.java:675)
        //     at com.strobel.decompiler.languages.java.ast.AstBuilder.addTypeMembers(AstBuilder.java:552)
        //     at com.strobel.decompiler.languages.java.ast.AstBuilder.createTypeCore(AstBuilder.java:519)
        //     at com.strobel.decompiler.languages.java.ast.AstBuilder.createTypeNoCache(AstBuilder.java:161)
        //     at com.strobel.decompiler.languages.java.ast.AstBuilder.createType(AstBuilder.java:150)
        //     at com.strobel.decompiler.languages.java.ast.AstBuilder.addType(AstBuilder.java:125)
        //     at com.strobel.decompiler.languages.java.JavaLanguage.buildAst(JavaLanguage.java:71)
        //     at com.strobel.decompiler.languages.java.JavaLanguage.decompileType(JavaLanguage.java:59)
        //     at com.strobel.decompiler.DecompilerDriver.decompileType(DecompilerDriver.java:330)
        //     at com.strobel.decompiler.DecompilerDriver.decompileJar(DecompilerDriver.java:251)
        //     at com.strobel.decompiler.DecompilerDriver.main(DecompilerDriver.java:126)
        // 
        throw new IllegalStateException("An error occurred while decompiling this method.");
    }
    
    @Override
    protected final void zzjD() {
    }
}
