// 
// Decompiled by Procyon v0.5.36
// 

package com.google.android.gms.tagmanager;

import com.google.android.gms.internal.zzbq;
import com.google.android.gms.internal.es;
import android.content.Context;

final class zzes implements Runnable
{
    private final Context mContext;
    private volatile String zzbDU;
    private final String zzbDw;
    private final es zzbFT;
    private final String zzbFU;
    private zzdi<zzbq> zzbFV;
    private volatile zzal zzbFW;
    private volatile String zzbFX;
    
    private zzes(final Context mContext, String value, final es zzbFT, final zzal zzbFW) {
        this.mContext = mContext;
        this.zzbFT = zzbFT;
        this.zzbDw = value;
        this.zzbFW = zzbFW;
        final String value2 = String.valueOf("/r?id=");
        value = String.valueOf(value);
        String concat;
        if (value.length() != 0) {
            concat = value2.concat(value);
        }
        else {
            concat = new String(value2);
        }
        this.zzbFU = concat;
        this.zzbDU = this.zzbFU;
        this.zzbFX = null;
    }
    
    public zzes(final Context context, final String s, final zzal zzal) {
        this(context, s, new es(), zzal);
    }
    
    @Override
    public final void run() {
        // 
        // This method could not be decompiled.
        // 
        // Original Bytecode:
        // 
        //     1: getfield        com/google/android/gms/tagmanager/zzes.zzbFV:Lcom/google/android/gms/tagmanager/zzdi;
        //     4: ifnonnull       17
        //     7: new             Ljava/lang/IllegalStateException;
        //    10: dup            
        //    11: ldc             "callback must be set before execute"
        //    13: invokespecial   java/lang/IllegalStateException.<init>:(Ljava/lang/String;)V
        //    16: athrow         
        //    17: aload_0        
        //    18: getfield        com/google/android/gms/tagmanager/zzes.mContext:Landroid/content/Context;
        //    21: ldc             "connectivity"
        //    23: invokevirtual   android/content/Context.getSystemService:(Ljava/lang/String;)Ljava/lang/Object;
        //    26: checkcast       Landroid/net/ConnectivityManager;
        //    29: invokevirtual   android/net/ConnectivityManager.getActiveNetworkInfo:()Landroid/net/NetworkInfo;
        //    32: astore_2       
        //    33: aload_2        
        //    34: ifnull          44
        //    37: aload_2        
        //    38: invokevirtual   android/net/NetworkInfo.isConnected:()Z
        //    41: ifne            68
        //    44: ldc             "...no network connectivity"
        //    46: invokestatic    com/google/android/gms/tagmanager/zzdj.v:(Ljava/lang/String;)V
        //    49: iconst_0       
        //    50: istore_1       
        //    51: iload_1        
        //    52: ifne            73
        //    55: aload_0        
        //    56: getfield        com/google/android/gms/tagmanager/zzes.zzbFV:Lcom/google/android/gms/tagmanager/zzdi;
        //    59: getstatic       com/google/android/gms/tagmanager/zzda.zzbFh:I
        //    62: invokeinterface com/google/android/gms/tagmanager/zzdi.zzbw:(I)V
        //    67: return         
        //    68: iconst_1       
        //    69: istore_1       
        //    70: goto            51
        //    73: ldc             "Start loading resource from network ..."
        //    75: invokestatic    com/google/android/gms/tagmanager/zzdj.v:(Ljava/lang/String;)V
        //    78: aload_0        
        //    79: getfield        com/google/android/gms/tagmanager/zzes.zzbFW:Lcom/google/android/gms/tagmanager/zzal;
        //    82: invokevirtual   com/google/android/gms/tagmanager/zzal.zzAX:()Ljava/lang/String;
        //    85: invokestatic    java/lang/String.valueOf:(Ljava/lang/Object;)Ljava/lang/String;
        //    88: astore_2       
        //    89: aload_0        
        //    90: getfield        com/google/android/gms/tagmanager/zzes.zzbDU:Ljava/lang/String;
        //    93: astore_3       
        //    94: ldc             "&v=a65833898"
        //    96: invokestatic    java/lang/String.valueOf:(Ljava/lang/Object;)Ljava/lang/String;
        //    99: astore          4
        //   101: new             Ljava/lang/StringBuilder;
        //   104: dup            
        //   105: aload_2        
        //   106: invokestatic    java/lang/String.valueOf:(Ljava/lang/Object;)Ljava/lang/String;
        //   109: invokevirtual   java/lang/String.length:()I
        //   112: aload_3        
        //   113: invokestatic    java/lang/String.valueOf:(Ljava/lang/Object;)Ljava/lang/String;
        //   116: invokevirtual   java/lang/String.length:()I
        //   119: iadd           
        //   120: aload           4
        //   122: invokestatic    java/lang/String.valueOf:(Ljava/lang/Object;)Ljava/lang/String;
        //   125: invokevirtual   java/lang/String.length:()I
        //   128: iadd           
        //   129: invokespecial   java/lang/StringBuilder.<init>:(I)V
        //   132: aload_2        
        //   133: invokevirtual   java/lang/StringBuilder.append:(Ljava/lang/String;)Ljava/lang/StringBuilder;
        //   136: aload_3        
        //   137: invokevirtual   java/lang/StringBuilder.append:(Ljava/lang/String;)Ljava/lang/StringBuilder;
        //   140: aload           4
        //   142: invokevirtual   java/lang/StringBuilder.append:(Ljava/lang/String;)Ljava/lang/StringBuilder;
        //   145: invokevirtual   java/lang/StringBuilder.toString:()Ljava/lang/String;
        //   148: astore_3       
        //   149: aload_3        
        //   150: astore_2       
        //   151: aload_0        
        //   152: getfield        com/google/android/gms/tagmanager/zzes.zzbFX:Ljava/lang/String;
        //   155: ifnull          240
        //   158: aload_3        
        //   159: astore_2       
        //   160: aload_0        
        //   161: getfield        com/google/android/gms/tagmanager/zzes.zzbFX:Ljava/lang/String;
        //   164: invokevirtual   java/lang/String.trim:()Ljava/lang/String;
        //   167: ldc             ""
        //   169: invokevirtual   java/lang/String.equals:(Ljava/lang/Object;)Z
        //   172: ifne            240
        //   175: aload_3        
        //   176: invokestatic    java/lang/String.valueOf:(Ljava/lang/Object;)Ljava/lang/String;
        //   179: astore_2       
        //   180: ldc             "&pv="
        //   182: invokestatic    java/lang/String.valueOf:(Ljava/lang/Object;)Ljava/lang/String;
        //   185: astore_3       
        //   186: aload_0        
        //   187: getfield        com/google/android/gms/tagmanager/zzes.zzbFX:Ljava/lang/String;
        //   190: astore          4
        //   192: new             Ljava/lang/StringBuilder;
        //   195: dup            
        //   196: aload_2        
        //   197: invokestatic    java/lang/String.valueOf:(Ljava/lang/Object;)Ljava/lang/String;
        //   200: invokevirtual   java/lang/String.length:()I
        //   203: aload_3        
        //   204: invokestatic    java/lang/String.valueOf:(Ljava/lang/Object;)Ljava/lang/String;
        //   207: invokevirtual   java/lang/String.length:()I
        //   210: iadd           
        //   211: aload           4
        //   213: invokestatic    java/lang/String.valueOf:(Ljava/lang/Object;)Ljava/lang/String;
        //   216: invokevirtual   java/lang/String.length:()I
        //   219: iadd           
        //   220: invokespecial   java/lang/StringBuilder.<init>:(I)V
        //   223: aload_2        
        //   224: invokevirtual   java/lang/StringBuilder.append:(Ljava/lang/String;)Ljava/lang/StringBuilder;
        //   227: aload_3        
        //   228: invokevirtual   java/lang/StringBuilder.append:(Ljava/lang/String;)Ljava/lang/StringBuilder;
        //   231: aload           4
        //   233: invokevirtual   java/lang/StringBuilder.append:(Ljava/lang/String;)Ljava/lang/StringBuilder;
        //   236: invokevirtual   java/lang/StringBuilder.toString:()Ljava/lang/String;
        //   239: astore_2       
        //   240: invokestatic    com/google/android/gms/tagmanager/zzei.zzBD:()Lcom/google/android/gms/tagmanager/zzei;
        //   243: invokevirtual   com/google/android/gms/tagmanager/zzei.zzBE:()Lcom/google/android/gms/tagmanager/zzei$zza;
        //   246: getstatic       com/google/android/gms/tagmanager/zzei$zza.zzbFL:Lcom/google/android/gms/tagmanager/zzei$zza;
        //   249: invokevirtual   com/google/android/gms/tagmanager/zzei$zza.equals:(Ljava/lang/Object;)Z
        //   252: ifeq            772
        //   255: aload_2        
        //   256: invokestatic    java/lang/String.valueOf:(Ljava/lang/Object;)Ljava/lang/String;
        //   259: astore_2       
        //   260: ldc             "&gtm_debug=x"
        //   262: invokestatic    java/lang/String.valueOf:(Ljava/lang/Object;)Ljava/lang/String;
        //   265: astore_3       
        //   266: aload_3        
        //   267: invokevirtual   java/lang/String.length:()I
        //   270: ifeq            438
        //   273: aload_2        
        //   274: aload_3        
        //   275: invokevirtual   java/lang/String.concat:(Ljava/lang/String;)Ljava/lang/String;
        //   278: astore_2       
        //   279: invokestatic    com/google/android/gms/internal/es.zzDF:()Lcom/google/android/gms/internal/er;
        //   282: astore          5
        //   284: aconst_null    
        //   285: astore          4
        //   287: aload           5
        //   289: aload_2        
        //   290: invokeinterface com/google/android/gms/internal/er.zzfU:(Ljava/lang/String;)Ljava/io/InputStream;
        //   295: astore_3       
        //   296: new             Ljava/io/ByteArrayOutputStream;
        //   299: dup            
        //   300: invokespecial   java/io/ByteArrayOutputStream.<init>:()V
        //   303: astore          4
        //   305: aload_3        
        //   306: aload           4
        //   308: invokestatic    com/google/android/gms/internal/eg.zzb:(Ljava/io/InputStream;Ljava/io/OutputStream;)V
        //   311: aload           4
        //   313: invokevirtual   java/io/ByteArrayOutputStream.toByteArray:()[B
        //   316: astore_3       
        //   317: new             Lcom/google/android/gms/internal/zzbq;
        //   320: dup            
        //   321: invokespecial   com/google/android/gms/internal/zzbq.<init>:()V
        //   324: aload_3        
        //   325: invokestatic    com/google/android/gms/internal/adp.zza:(Lcom/google/android/gms/internal/adp;[B)Lcom/google/android/gms/internal/adp;
        //   328: checkcast       Lcom/google/android/gms/internal/zzbq;
        //   331: astore          4
        //   333: aload           4
        //   335: invokestatic    java/lang/String.valueOf:(Ljava/lang/Object;)Ljava/lang/String;
        //   338: astore_3       
        //   339: new             Ljava/lang/StringBuilder;
        //   342: dup            
        //   343: aload_3        
        //   344: invokestatic    java/lang/String.valueOf:(Ljava/lang/Object;)Ljava/lang/String;
        //   347: invokevirtual   java/lang/String.length:()I
        //   350: bipush          43
        //   352: iadd           
        //   353: invokespecial   java/lang/StringBuilder.<init>:(I)V
        //   356: ldc             "Successfully loaded supplemented resource: "
        //   358: invokevirtual   java/lang/StringBuilder.append:(Ljava/lang/String;)Ljava/lang/StringBuilder;
        //   361: aload_3        
        //   362: invokevirtual   java/lang/StringBuilder.append:(Ljava/lang/String;)Ljava/lang/StringBuilder;
        //   365: invokevirtual   java/lang/StringBuilder.toString:()Ljava/lang/String;
        //   368: invokestatic    com/google/android/gms/tagmanager/zzdj.v:(Ljava/lang/String;)V
        //   371: aload           4
        //   373: getfield        com/google/android/gms/internal/zzbq.zzlB:Lcom/google/android/gms/internal/zzbn;
        //   376: ifnonnull       414
        //   379: aload           4
        //   381: getfield        com/google/android/gms/internal/zzbq.zzlA:[Lcom/google/android/gms/internal/zzbp;
        //   384: arraylength    
        //   385: ifne            414
        //   388: aload_0        
        //   389: getfield        com/google/android/gms/tagmanager/zzes.zzbDw:Ljava/lang/String;
        //   392: invokestatic    java/lang/String.valueOf:(Ljava/lang/Object;)Ljava/lang/String;
        //   395: astore_3       
        //   396: aload_3        
        //   397: invokevirtual   java/lang/String.length:()I
        //   400: ifeq            677
        //   403: ldc             "No change for container: "
        //   405: aload_3        
        //   406: invokevirtual   java/lang/String.concat:(Ljava/lang/String;)Ljava/lang/String;
        //   409: astore_3       
        //   410: aload_3        
        //   411: invokestatic    com/google/android/gms/tagmanager/zzdj.v:(Ljava/lang/String;)V
        //   414: aload_0        
        //   415: getfield        com/google/android/gms/tagmanager/zzes.zzbFV:Lcom/google/android/gms/tagmanager/zzdi;
        //   418: aload           4
        //   420: invokeinterface com/google/android/gms/tagmanager/zzdi.onSuccess:(Ljava/lang/Object;)V
        //   425: aload           5
        //   427: invokeinterface com/google/android/gms/internal/er.close:()V
        //   432: ldc             "Load resource from network finished."
        //   434: invokestatic    com/google/android/gms/tagmanager/zzdj.v:(Ljava/lang/String;)V
        //   437: return         
        //   438: new             Ljava/lang/String;
        //   441: dup            
        //   442: aload_2        
        //   443: invokespecial   java/lang/String.<init>:(Ljava/lang/String;)V
        //   446: astore_2       
        //   447: goto            279
        //   450: astore_3       
        //   451: aload_0        
        //   452: getfield        com/google/android/gms/tagmanager/zzes.zzbDw:Ljava/lang/String;
        //   455: astore_3       
        //   456: new             Ljava/lang/StringBuilder;
        //   459: dup            
        //   460: aload_2        
        //   461: invokestatic    java/lang/String.valueOf:(Ljava/lang/Object;)Ljava/lang/String;
        //   464: invokevirtual   java/lang/String.length:()I
        //   467: bipush          79
        //   469: iadd           
        //   470: aload_3        
        //   471: invokestatic    java/lang/String.valueOf:(Ljava/lang/Object;)Ljava/lang/String;
        //   474: invokevirtual   java/lang/String.length:()I
        //   477: iadd           
        //   478: invokespecial   java/lang/StringBuilder.<init>:(I)V
        //   481: ldc             "No data is retrieved from the given url: "
        //   483: invokevirtual   java/lang/StringBuilder.append:(Ljava/lang/String;)Ljava/lang/StringBuilder;
        //   486: aload_2        
        //   487: invokevirtual   java/lang/StringBuilder.append:(Ljava/lang/String;)Ljava/lang/StringBuilder;
        //   490: ldc             ". Make sure container_id: "
        //   492: invokevirtual   java/lang/StringBuilder.append:(Ljava/lang/String;)Ljava/lang/StringBuilder;
        //   495: aload_3        
        //   496: invokevirtual   java/lang/StringBuilder.append:(Ljava/lang/String;)Ljava/lang/StringBuilder;
        //   499: ldc             " is correct."
        //   501: invokevirtual   java/lang/StringBuilder.append:(Ljava/lang/String;)Ljava/lang/StringBuilder;
        //   504: invokevirtual   java/lang/StringBuilder.toString:()Ljava/lang/String;
        //   507: invokestatic    com/google/android/gms/tagmanager/zzdj.zzaT:(Ljava/lang/String;)V
        //   510: aload_0        
        //   511: getfield        com/google/android/gms/tagmanager/zzes.zzbFV:Lcom/google/android/gms/tagmanager/zzdi;
        //   514: getstatic       com/google/android/gms/tagmanager/zzda.zzbFj:I
        //   517: invokeinterface com/google/android/gms/tagmanager/zzdi.zzbw:(I)V
        //   522: aload           5
        //   524: invokeinterface com/google/android/gms/internal/er.close:()V
        //   529: return         
        //   530: astore_3       
        //   531: aload_2        
        //   532: invokestatic    java/lang/String.valueOf:(Ljava/lang/Object;)Ljava/lang/String;
        //   535: astore_3       
        //   536: aload_3        
        //   537: invokevirtual   java/lang/String.length:()I
        //   540: ifeq            582
        //   543: ldc             "Error when loading resource for url: "
        //   545: aload_3        
        //   546: invokevirtual   java/lang/String.concat:(Ljava/lang/String;)Ljava/lang/String;
        //   549: astore_3       
        //   550: aload_3        
        //   551: invokestatic    com/google/android/gms/tagmanager/zzdj.zzaT:(Ljava/lang/String;)V
        //   554: aload_0        
        //   555: getfield        com/google/android/gms/tagmanager/zzes.zzbFV:Lcom/google/android/gms/tagmanager/zzdi;
        //   558: getstatic       com/google/android/gms/tagmanager/zzda.zzbFk:I
        //   561: invokeinterface com/google/android/gms/tagmanager/zzdi.zzbw:(I)V
        //   566: aload           4
        //   568: astore_3       
        //   569: goto            296
        //   572: astore_2       
        //   573: aload           5
        //   575: invokeinterface com/google/android/gms/internal/er.close:()V
        //   580: aload_2        
        //   581: athrow         
        //   582: new             Ljava/lang/String;
        //   585: dup            
        //   586: ldc             "Error when loading resource for url: "
        //   588: invokespecial   java/lang/String.<init>:(Ljava/lang/String;)V
        //   591: astore_3       
        //   592: goto            550
        //   595: astore_3       
        //   596: aload_3        
        //   597: invokevirtual   java/io/IOException.getMessage:()Ljava/lang/String;
        //   600: invokestatic    java/lang/String.valueOf:(Ljava/lang/Object;)Ljava/lang/String;
        //   603: astore          4
        //   605: new             Ljava/lang/StringBuilder;
        //   608: dup            
        //   609: aload_2        
        //   610: invokestatic    java/lang/String.valueOf:(Ljava/lang/Object;)Ljava/lang/String;
        //   613: invokevirtual   java/lang/String.length:()I
        //   616: bipush          40
        //   618: iadd           
        //   619: aload           4
        //   621: invokestatic    java/lang/String.valueOf:(Ljava/lang/Object;)Ljava/lang/String;
        //   624: invokevirtual   java/lang/String.length:()I
        //   627: iadd           
        //   628: invokespecial   java/lang/StringBuilder.<init>:(I)V
        //   631: ldc             "Error when loading resources from url: "
        //   633: invokevirtual   java/lang/StringBuilder.append:(Ljava/lang/String;)Ljava/lang/StringBuilder;
        //   636: aload_2        
        //   637: invokevirtual   java/lang/StringBuilder.append:(Ljava/lang/String;)Ljava/lang/StringBuilder;
        //   640: ldc             " "
        //   642: invokevirtual   java/lang/StringBuilder.append:(Ljava/lang/String;)Ljava/lang/StringBuilder;
        //   645: aload           4
        //   647: invokevirtual   java/lang/StringBuilder.append:(Ljava/lang/String;)Ljava/lang/StringBuilder;
        //   650: invokevirtual   java/lang/StringBuilder.toString:()Ljava/lang/String;
        //   653: aload_3        
        //   654: invokestatic    com/google/android/gms/tagmanager/zzdj.zzc:(Ljava/lang/String;Ljava/lang/Throwable;)V
        //   657: aload_0        
        //   658: getfield        com/google/android/gms/tagmanager/zzes.zzbFV:Lcom/google/android/gms/tagmanager/zzdi;
        //   661: getstatic       com/google/android/gms/tagmanager/zzda.zzbFi:I
        //   664: invokeinterface com/google/android/gms/tagmanager/zzdi.zzbw:(I)V
        //   669: aload           5
        //   671: invokeinterface com/google/android/gms/internal/er.close:()V
        //   676: return         
        //   677: new             Ljava/lang/String;
        //   680: dup            
        //   681: ldc             "No change for container: "
        //   683: invokespecial   java/lang/String.<init>:(Ljava/lang/String;)V
        //   686: astore_3       
        //   687: goto            410
        //   690: astore_3       
        //   691: aload_3        
        //   692: invokevirtual   java/io/IOException.getMessage:()Ljava/lang/String;
        //   695: invokestatic    java/lang/String.valueOf:(Ljava/lang/Object;)Ljava/lang/String;
        //   698: astore          4
        //   700: new             Ljava/lang/StringBuilder;
        //   703: dup            
        //   704: aload_2        
        //   705: invokestatic    java/lang/String.valueOf:(Ljava/lang/Object;)Ljava/lang/String;
        //   708: invokevirtual   java/lang/String.length:()I
        //   711: bipush          51
        //   713: iadd           
        //   714: aload           4
        //   716: invokestatic    java/lang/String.valueOf:(Ljava/lang/Object;)Ljava/lang/String;
        //   719: invokevirtual   java/lang/String.length:()I
        //   722: iadd           
        //   723: invokespecial   java/lang/StringBuilder.<init>:(I)V
        //   726: ldc             "Error when parsing downloaded resources from url: "
        //   728: invokevirtual   java/lang/StringBuilder.append:(Ljava/lang/String;)Ljava/lang/StringBuilder;
        //   731: aload_2        
        //   732: invokevirtual   java/lang/StringBuilder.append:(Ljava/lang/String;)Ljava/lang/StringBuilder;
        //   735: ldc             " "
        //   737: invokevirtual   java/lang/StringBuilder.append:(Ljava/lang/String;)Ljava/lang/StringBuilder;
        //   740: aload           4
        //   742: invokevirtual   java/lang/StringBuilder.append:(Ljava/lang/String;)Ljava/lang/StringBuilder;
        //   745: invokevirtual   java/lang/StringBuilder.toString:()Ljava/lang/String;
        //   748: aload_3        
        //   749: invokestatic    com/google/android/gms/tagmanager/zzdj.zzc:(Ljava/lang/String;Ljava/lang/Throwable;)V
        //   752: aload_0        
        //   753: getfield        com/google/android/gms/tagmanager/zzes.zzbFV:Lcom/google/android/gms/tagmanager/zzdi;
        //   756: getstatic       com/google/android/gms/tagmanager/zzda.zzbFj:I
        //   759: invokeinterface com/google/android/gms/tagmanager/zzdi.zzbw:(I)V
        //   764: aload           5
        //   766: invokeinterface com/google/android/gms/internal/er.close:()V
        //   771: return         
        //   772: goto            279
        //    Exceptions:
        //  Try           Handler
        //  Start  End    Start  End    Type                                
        //  -----  -----  -----  -----  ------------------------------------
        //  287    296    450    530    Ljava/io/FileNotFoundException;
        //  287    296    530    595    Lcom/google/android/gms/internal/et;
        //  287    296    595    677    Ljava/io/IOException;
        //  287    296    572    582    Any
        //  296    410    690    772    Ljava/io/IOException;
        //  296    410    572    582    Any
        //  410    414    690    772    Ljava/io/IOException;
        //  410    414    572    582    Any
        //  414    425    690    772    Ljava/io/IOException;
        //  414    425    572    582    Any
        //  451    522    572    582    Any
        //  531    550    572    582    Any
        //  550    566    572    582    Any
        //  582    592    572    582    Any
        //  596    669    572    582    Any
        //  677    687    690    772    Ljava/io/IOException;
        //  677    687    572    582    Any
        //  691    764    572    582    Any
        // 
        // The error that occurred was:
        // 
        // java.lang.IllegalStateException: Expression is linked from several locations: Label_0296:
        //     at com.strobel.decompiler.ast.Error.expressionLinkedFromMultipleLocations(Error.java:27)
        //     at com.strobel.decompiler.ast.AstOptimizer.mergeDisparateObjectInitializations(AstOptimizer.java:2596)
        //     at com.strobel.decompiler.ast.AstOptimizer.optimize(AstOptimizer.java:235)
        //     at com.strobel.decompiler.ast.AstOptimizer.optimize(AstOptimizer.java:42)
        //     at com.strobel.decompiler.languages.java.ast.AstMethodBodyBuilder.createMethodBody(AstMethodBodyBuilder.java:214)
        //     at com.strobel.decompiler.languages.java.ast.AstMethodBodyBuilder.createMethodBody(AstMethodBodyBuilder.java:99)
        //     at com.strobel.decompiler.languages.java.ast.AstBuilder.createMethodBody(AstBuilder.java:782)
        //     at com.strobel.decompiler.languages.java.ast.AstBuilder.createMethod(AstBuilder.java:675)
        //     at com.strobel.decompiler.languages.java.ast.AstBuilder.addTypeMembers(AstBuilder.java:552)
        //     at com.strobel.decompiler.languages.java.ast.AstBuilder.createTypeCore(AstBuilder.java:519)
        //     at com.strobel.decompiler.languages.java.ast.AstBuilder.createTypeNoCache(AstBuilder.java:161)
        //     at com.strobel.decompiler.languages.java.ast.AstBuilder.createType(AstBuilder.java:150)
        //     at com.strobel.decompiler.languages.java.ast.AstBuilder.addType(AstBuilder.java:125)
        //     at com.strobel.decompiler.languages.java.JavaLanguage.buildAst(JavaLanguage.java:71)
        //     at com.strobel.decompiler.languages.java.JavaLanguage.decompileType(JavaLanguage.java:59)
        //     at com.strobel.decompiler.DecompilerDriver.decompileType(DecompilerDriver.java:330)
        //     at com.strobel.decompiler.DecompilerDriver.decompileJar(DecompilerDriver.java:251)
        //     at com.strobel.decompiler.DecompilerDriver.main(DecompilerDriver.java:126)
        // 
        throw new IllegalStateException("An error occurred while decompiling this method.");
    }
    
    final void zza(final zzdi<zzbq> zzbFV) {
        this.zzbFV = zzbFV;
    }
    
    final void zzfb(final String s) {
        if (s == null) {
            this.zzbDU = this.zzbFU;
            return;
        }
        final String value = String.valueOf(s);
        String concat;
        if (value.length() != 0) {
            concat = "Setting CTFE URL path: ".concat(value);
        }
        else {
            concat = new String("Setting CTFE URL path: ");
        }
        zzdj.zzaC(concat);
        this.zzbDU = s;
    }
    
    final void zzfr(final String s) {
        final String value = String.valueOf(s);
        String concat;
        if (value.length() != 0) {
            concat = "Setting previous container version: ".concat(value);
        }
        else {
            concat = new String("Setting previous container version: ");
        }
        zzdj.zzaC(concat);
        this.zzbFX = s;
    }
}
